Workbook
Name Slicer_Request_Month: #N/A
Name Slicer_Shipment_Month: #N/A
Name Slicer_Shipped_Year: #N/A
Name Slicer_Year: #N/A

Sheet PIV
B4: FIELD QUALITY REPORT | T4: Manufacturing Cohort Analysis
B7: Issue Reported Date | C7: (Multiple Items)
B8: Status | C8: (All)
B9: MC Type | C9: (All)
B10: Replacement Type | C10: (All)
B12: Count of MachineSerialNumber | D12: Year | E12: Request Month | T12: Delivered Units to Customer | U12: Pending Number of RMA Units | V12: Field RMA Rate by Cohort
D13: 2025 | L13: 2026 | S13: Total RMA Units
B14: Shipped Year | C14: Shipment Month | D14: May | E14: Jun | F14: Jul | G14: Aug | H14: Sep | I14: Oct | J14: Nov | K14: Dec | L14: Jan | M14: Feb | N14: Mar | O14: Apr | P14: May | Q14: Jun | R14: Jul
B15: 2025 | C15: Jan | D15: 2 | F15: 2 | H15: 1 | I15: 1 | K15: 2 | L15: 3 | M15: 2 | N15: 1 | S15: 14 | T15: - | U15: - | V15: =IFERROR((#REF!+U15)/T15,"")
C16: Feb | D16: 8 | E16: 2 | F16: 2 | G16: 1 | H16: 1 | J16: 1 | K16: 2 | L16: 1 | M16: 5 | S16: 23 | T16: - | U16: - | V16: =IFERROR((#REF!+U16)/T16,"")
C17: Mar | D17: 25 | E17: 2 | F17: 7 | G17: 5 | H17: 2 | I17: 5 | J17: 2 | K17: 2 | L17: 4 | M17: 1 | N17: 1 | O17: 1 | P17: 2 | R17: 1 | S17: 60 | T17: - | U17: - | V17: =IFERROR((#REF!+U17)/T17,"")
C18: Apr | D18: 17 | E18: 31 | F18: 29 | G18: 13 | H18: 18 | I18: 4 | J18: 6 | K18: 2 | L18: 2 | M18: 6 | O18: 1 | P18: 1 | Q18: 1 | R18: 3 | S18: 134 | T18: - | U18: - | V18: =IFERROR((#REF!+U18)/T18,"")
C19: May | D19: 1 | E19: 18 | F19: 20 | G19: 16 | H19: 15 | I19: 5 | J19: 8 | K19: 8 | L19: 7 | M19: 5 | N19: 6 | O19: 2 | P19: 1 | Q19: 2 | R19: 4 | S19: 118 | T19: 138 | U19: 2 | V19: =IFERROR((S19+U19)/T19,"") -> 0.86956522
C20: Jun | E20: 23 | F20: 88 | G20: 84 | H20: 99 | I20: 53 | J20: 50 | K20: 47 | L20: 41 | M20: 33 | N20: 23 | O20: 10 | P20: 9 | Q20: 14 | R20: 21 | S20: 595 | T20: 1004 | U20: 11 | V20: =IFERROR((S20+U20)/T20,"") -> 0.60358566
C21: Jul | E21: 1 | F21: 29 | G21: 81 | H21: 106 | I21: 52 | J21: 59 | K21: 69 | L21: 54 | M21: 51 | N21: 12 | O21: 23 | P21: 23 | Q21: 10 | R21: 30 | S21: 600 | T21: 1081 | U21: 12 | V21: =IFERROR((S21+U21)/T21,"") -> 0.56614246
C22: Aug | F22: 1 | G22: 8 | H22: 96 | I22: 71 | J22: 63 | K22: 65 | L22: 64 | M22: 44 | N22: 5 | O22: 30 | P22: 8 | Q22: 9 | R22: 27 | S22: 491 | T22: 956 | U22: 4 | V22: =IFERROR((S22+U22)/T22,"") -> 0.51778243
C23: Sep | H23: 11 | I23: 40 | J23: 53 | K23: 57 | L23: 44 | M23: 44 | N23: 19 | O23: 26 | P23: 19 | Q23: 12 | R23: 22 | S23: 347 | T23: 840 | U23: 5 | V23: =IFERROR((S23+U23)/T23,"") -> 0.41904762
C24: Oct | H24: 1 | I24: 2 | J24: 42 | K24: 69 | L24: 44 | M24: 43 | N24: 12 | O24: 16 | P24: 19 | Q24: 13 | R24: 25 | S24: 286 | T24: 921 | U24: 9 | V24: =IFERROR((S24+U24)/T24,"") -> 0.32030402
C25: Nov | J25: 5 | K25: 144 | L25: 88 | M25: 92 | N25: 25 | O25: 36 | P25: 36 | Q25: 31 | R25: 40 | S25: 497 | T25: 1742 | U25: 24 | V25: =IFERROR((S25+U25)/T25,"") -> 0.29908152
C26: Dec | K26: 12 | L26: 163 | M26: 131 | N26: 38 | O26: 44 | P26: 37 | Q26: 40 | R26: 53 | S26: 518 | T26: 2242 | U26: 12 | V26: =IFERROR((S26+U26)/T26,"") -> 0.23639607
B27: 2026 | C27: Jan | L27: 1 | M27: 5 | N27: 7 | O27: 17 | P27: 26 | Q27: 24 | R27: 47 | S27: 127 | T27: 278 | U27: 16 | V27: =IFERROR((S27+U27)/T27,"") -> 0.51438849
C28: Feb | M28: 3 | N28: 11 | O28: 36 | P28: 30 | Q28: 16 | R28: 46 | S28: 142 | T28: 786 | U28: 21 | V28: =IFERROR((S28+U28)/T28,"") -> 0.20737913
C29: Mar | P29: 3 | Q29: 7 | R29: 10 | S29: 20 | T29: 598 | U29: 2 | V29: =IFERROR((S29+U29)/T29,"") -> 0.036789298
C30: Apr | P30: 2 | Q30: 14 | R30: 13 | S30: 29 | T30: 733 | U30: 1 | V30: =IFERROR((S30+U30)/T30,"") -> 0.040927694
B31: Total RMA Units | D31: 53 | E31: 77 | F31: 178 | G31: 208 | H31: 350 | I31: 233 | J31: 289 | K31: 479 | L31: 516 | M31: 465 | N31: 160 | O31: 242 | P31: 216 | Q31: 193 | R31: 342 | S31: 4001 | T31: 616
B32: Total Delivered RMA Units | D32: =T19 -> 138 | E32: =T20 -> 1004 | F32: =T21 -> 1081 | G32: =T22 -> 956 | H32: =T23 -> 840 | I32: =T24 -> 921 | J32: =T25 -> 1742 | K32: =T26 -> 2242 | L32: =T27 -> 278 | M32: =T28 -> 786 | N32: =T29 -> 598 | O32: =T30 -> 733 | P32: =T31 -> 616 | Q32: 0 | R32: 0
B33: Active Units in the Field | D33: =D32 -> 138 | E33: =(E32-D31)+D33 -> 1089 | F33: =(F32-E31)+E33 -> 2093 | G33: =(G32-F31)+F33 -> 2871 | H33: =(H32-G31)+G33 -> 3503 | I33: =(I32-H31)+H33 -> 4074 | J33: =(J32-I31)+I33 -> 5583 | K33: =(K32-J31)+J33 -> 7536 | L33: =(L32-K31)+K33 -> 7335 | ... R33: =(R32-Q31)+Q33 -> 8276
B34: Reported Field RMA Rate | D34: =IFERROR(D31/D33,"") -> 0.38405797 | E34: =IFERROR(E31/E33,"") -> 0.070707071 | F34: =IFERROR(F31/F33,"") -> 0.085045389 | G34: =IFERROR(G31/G33,"") -> 0.072448624 | H34: =IFERROR(H31/H33,"") -> 0.099914359 | I34: =IFERROR(I31/I33,"") -> 0.057191949 | J34: =IFERROR(J31/J33,"") -> 0.051764284 | K34: =IFERROR(K31/K33,"") -> 0.063561571 | ... R34: =IFERROR(R31/R33,"") -> 0.041324311
B37: Year | C37: (All)
B38: Request Month | C38: (All)
B40: Shipped Year | C40: Shipment Month | D40: WW Code | E40: Count of MachineSerialNumber
B41: 2025 | C41: Jan | D41: 04 | E41: 4
D42: 09 | E42: 7
D43: CA | E43: 2
D44: ME | E44: 1
C45: Feb | D45: 08 | E45: 3
D46: 09 | E46: 12
D47: 13 | E47: 1
D48: 1C | E48: 3
D49: CA | E49: 4
C50: Mar | D50: 10 | E50: 14
D51: 11 | E51: 5
D52: 12 | E52: 27
D53: 13 | E53: 9
D54: CA | E54: 5
C55: Apr | D55: 14 | E55: 2
D56: 15 | E56: 12
D57: 16 | E57: 32
D58: 17 | E58: 84
D59: 18 | E59: 3
D60: 20 | E60: 1
C61: May | D61: 12 | E61: 1
D62: 14 | E62: 1
D63: 18 | E63: 9
D64: 19 | E64: 24
D65: 20 | E65: 4
D66: 21 | E66: 40
D67: 22 | E67: 37
D68: 23 | E68: 1
D69: 50 | E69: 1
C70: Jun | D70: 02 | E70: 1
D71: 07 | E71: 1
D72: 22 | E72: 1
D73: 23 | E73: 92
D74: 24 | E74: 107
D75: 25 | E75: 152
D76: 26 | E76: 200
D77: 27 | E77: 40
D78: 7M | E78: 1
C79: Jul | D79: 27 | E79: 79
D80: 28 | E80: 159
D81: 29 | E81: 146
D82: 30 | E82: 104
D83: 31 | E83: 110
D84: ME | E84: 3
C85: Aug | D85: 23 | E85: 1
D86: 32 | E86: 106
D87: 33 | E87: 38
D88: 34 | E88: 184
D89: 35 | E89: 116
D90: 36 | E90: 44
D91: 42 | E91: 1
D92: CA | E92: 1
C93: Sep | D93: 36 | E93: 8
D94: 37 | E94: 82
D95: 38 | E95: 24
D96: 39 | E96: 89
D97: 40 | E97: 140
D98: 41 | E98: 1
D99: 4M | E99: 1
D100: CA | E100: 2
C101: Oct | D101: 41 | E101: 35
D102: 42 | E102: 45
D103: 43 | E103: 199
D104: 4M | E104: 1
D105: CA | E105: 4
D106: ME | E106: 2
C107: Nov | D107: 44 | E107: 179
D108: 46 | E108: 164
D109: 47 | E109: 156
...

Sheet Product Performance
B2: Field Quality Report | J2: Manufacturing Cohort Analysis | Q2: Cummulative Quarterly Performance Per Manufacturing Cohort | AG2: Cumulative RMA Failure Rate by Manufacturing Cohort and Aging Interval | BA2: Failure.Failure Category | BB2: Count of MachineSerialNumber | BD2: Failure.Failure Mode | BE2: Count of MachineSerialNumber
B3: Shipment Year | C3: Shipment Month | D3: Total RMA Units | E3: Total Delivered RMA Units | F3: Active Units in the Field | G3: Reported Field RMA Rate | J3: Shipment Year | K3: Shipment Month | L3: Total RMA Units | M3: Delivered Units to Customer | N3: Pending Number of RMA Units | O3: Field RMA Rate by Cohort | Q3: Year | R3: Quarter | S3: Delivered Units | T3: M0 (3-month offset) | U3: M+1 | V3: M+2 | W3: M+3 | X3: M+4 | Y3: M+5 | Z3: M+6 | AA3: M+7 | AB3: M+8 | AC3: M+9 | AD3: M+10 | AE3: M+11 | AG3: Shipment Year | AH3: Shipment Month | AI3: Delivered Units | AJ3: 0–3 Months | AK3: 3–6 Months | AL3: 6–9 Months | AM3: 9–12 Months | AN3: 12–15 Months | AO3: 15–18 Months | BA3: Kicker Module | BB3: 1060 | BD3: Not Powering On | BE3: 699
B4: 2025 | C4: May | D4: 53 | E4: 138 | F4: 138 | G4: 0.38405797 | J4: 2025 | K4: May | L4: 114 | M4: 138 | N4: 2 | O4: 0.84057971 | Q4: 2025 | R4: Qtr2 | S4: 1142 | T4: 0.20490368 | U4: 0.3056042 | V4: 0.36514886 | W4: 0.41330998 | X4: 0.4614711 | Y4: 0.50437828 | Z4: 0.53940455 | AA4: 0.56392294 | AB4: 0.57793345 | AC4: 0.58756567 | AD4: 0.60070053 | AE4: 0.61646235 | AG4: 2025 | AH4: May | AI4: 138 | AJ4: =IF(SUM(OFFSET($T$50,0,(COLUMN()-COLUMN($AJ$4))*3,1,3))=0,"",SUM(OFFSET($T$50,0,(COLUMN()-COLUMN($AJ$4))*3,1,3))) -> 0.2826087 | AK4: =IFERROR(IF(SUM(OFFSET($T$50,0,(COLUMN()-COLUMN($AJ$4))*3,1,3))=0,"",SUM(OFFSET($T$50,0,(COLUMN()-COLUMN($AJ$4))*3,1,3)))+AJ4,"") -> 0.54347826 | AL4: =IFERROR(IF(SUM(OFFSET($T$50,0,(COLUMN()-COLUMN($AJ$4))*3,1,3))=0,"",SUM(OFFSET($T$50,0,(COLUMN()-COLUMN($AJ$4))*3,1,3)))+AK4,"") -> 0.71014493 | AM4: =IFERROR(IF(SUM(OFFSET($T$50,0,(COLUMN()-COLUMN($AJ$4))*3,1,3))=0,"",SUM(OFFSET($T$50,0,(COLUMN()-COLUMN($AJ$4))*3,1,3)))+AL4,"") -> 0.80434783 | AN4: =IFERROR(IF(SUM(OFFSET($T$50,0,(COLUMN()-COLUMN($AJ$4))*3,1,3))=0,"",SUM(OFFSET($T$50,0,(COLUMN()-COLUMN($AJ$4))*3,1,3)))+AM4,"") -> 0.85507246 | AO4: =IFERROR(IF(SUM(OFFSET($T$50,0,(COLUMN()-COLUMN($AJ$4))*3,1,3))=0,"",SUM(OFFSET($T$50,0,(COLUMN()-COLUMN($AJ$4))*3,1,3)))+AN4,"") | BA4: Electrical | BB4: 797 | BD4: Kicker Drive | BE4: 617
C5: Jun | D5: 77 | E5: 1004 | F5: 1089 | G5: 0.070707071 | K5: Jun | L5: 574 | M5: 1004 | N5: 11 | O5: 0.58266932 | R5: Qtr3 | S5: 2877 | T5: 0.17274939 | U5: 0.23253389 | V5: 0.29092805 | W5: 0.35245047 | X5: 0.39311783 | Y5: 0.42161974 | Z5: 0.44282238 | AA5: 0.45776851 | AB5: 0.47480014 | AC5: 0.48522767 | AH5: Jun | AI5: 1004 | AJ5: =IF(SUM(OFFSET($U$51,0,(COLUMN()-COLUMN($AJ$4))*3,1,3))=0,"",SUM(OFFSET($U$51,0,(COLUMN()-COLUMN($AJ$4))*3,1,3))) -> 0.19422311 | AK5: =IFERROR(IF(SUM(OFFSET($U$51,0,(COLUMN()-COLUMN($AJ$4))*3,1,3))=0,"",SUM(OFFSET($U$51,0,(COLUMN()-COLUMN($AJ$4))*3,1,3)))+AJ5,"") -> 0.39541833 | AL5: =IFERROR(IF(SUM(OFFSET($U$51,0,(COLUMN()-COLUMN($AJ$4))*3,1,3))=0,"",SUM(OFFSET($U$51,0,(COLUMN()-COLUMN($AJ$4))*3,1,3)))+AK5,"") -> 0.51593625 | AM5: =IFERROR(IF(SUM(OFFSET($U$51,0,(COLUMN()-COLUMN($AJ$4))*3,1,3))=0,"",SUM(OFFSET($U$51,0,(COLUMN()-COLUMN($AJ$4))*3,1,3)))+AL5,"") -> 0.55776892 | AN5: =IFERROR(IF(SUM(OFFSET($U$51,0,(COLUMN()-COLUMN($AJ$4))*3,1,3))=0,"",SUM(OFFSET($U$51,0,(COLUMN()-COLUMN($AJ$4))*3,1,3)))+AM5,"") -> 0.59262948 | AO5: =IFERROR(IF(SUM(OFFSET($U$51,0,(COLUMN()-COLUMN($AJ$4))*3,1,3))=0,"",SUM(OFFSET($U$51,0,(COLUMN()-COLUMN($AJ$4))*3,1,3)))+AN5,"") | BA5: Kneader | BB5: 355 | BD5: Administrative Note | BE5: 268
C6: Jul | D6: 178 | E6: 1081 | F6: 2093 | G6: 0.085045389 | K6: Jul | L6: 582 | M6: 1081 | N6: 12 | O6: 0.54949121 | R6: Qtr4 | S6: 4905 | T6: 0.13394495 | U6: 0.16941896 | V6: 0.19245668 | W6: 0.20998981 | X6: 0.22895005 | Y6: 0.2479103 | Z6: 0.25688073 | AA6: 0.26055046 | AH6: Jul | AI6: 1081 | AJ6: =IF(SUM(OFFSET($V$52,0,(COLUMN()-COLUMN($AJ$4))*3,1,3))=0,"",SUM(OFFSET($V$52,0,(COLUMN()-COLUMN($AJ$4))*3,1,3))) -> 0.19981499 | AK6: =IFERROR(IF(SUM(OFFSET($V$52,0,(COLUMN()-COLUMN($AJ$4))*3,1,3))=0,"",SUM(OFFSET($V$52,0,(COLUMN()-COLUMN($AJ$4))*3,1,3)))+AJ6,"") -> 0.36632747 | AL6: =IFERROR(IF(SUM(OFFSET($V$52,0,(COLUMN()-COLUMN($AJ$4))*3,1,3))=0,"",SUM(OFFSET($V$52,0,(COLUMN()-COLUMN($AJ$4))*3,1,3)))+AK6,"") -> 0.47456059 | AM6: =IFERROR(IF(SUM(OFFSET($V$52,0,(COLUMN()-COLUMN($AJ$4))*3,1,3))=0,"",SUM(OFFSET($V$52,0,(COLUMN()-COLUMN($AJ$4))*3,1,3)))+AL6,"") -> 0.52636448 | AN6: =IFERROR(IF(SUM(OFFSET($V$52,0,(COLUMN()-COLUMN($AJ$4))*3,1,3))=0,"",SUM(OFFSET($V$52,0,(COLUMN()-COLUMN($AJ$4))*3,1,3)))+AM6,"") -> 0.55411656 | AO6: =IFERROR(IF(SUM(OFFSET($V$52,0,(COLUMN()-COLUMN($AJ$4))*3,1,3))=0,"",SUM(OFFSET($V$52,0,(COLUMN()-COLUMN($AJ$4))*3,1,3)))+AN6,"") | BA6: Administrative | BB6: 296 | BD6: Kicker Noise | BE6: 225
C7: Aug | D7: 208 | E7: 956 | F7: 2871 | G7: 0.072448624 | K7: Aug | L7: 465 | M7: 956 | N7: 4 | O7: 0.49058577 | Q7: 2026 | R7: Qtr1 | S7: 1662 | T7: 0.039711191 | U7: 0.072803851 | V7: 0.10168472 | W7: 0.13658243 | X7: 0.16185319 | AH7: Aug | AI7: 956 | AJ7: =IF(SUM(OFFSET($W$53,0,(COLUMN()-COLUMN($AJ$4))*3,1,3))=0,"",SUM(OFFSET($W$53,0,(COLUMN()-COLUMN($AJ$4))*3,1,3))) -> 0.18305439 | AK7: =IFERROR(IF(SUM(OFFSET($W$53,0,(COLUMN()-COLUMN($AJ$4))*3,1,3))=0,"",SUM(OFFSET($W$53,0,(COLUMN()-COLUMN($AJ$4))*3,1,3)))+AJ7,"") -> 0.38389121 | AL7: =IFERROR(IF(SUM(OFFSET($W$53,0,(COLUMN()-COLUMN($AJ$4))*3,1,3))=0,"",SUM(OFFSET($W$53,0,(COLUMN()-COLUMN($AJ$4))*3,1,3)))+AK7,"") -> 0.4665272 | AM7: =IFERROR(IF(SUM(OFFSET($W$53,0,(COLUMN()-COLUMN($AJ$4))*3,1,3))=0,"",SUM(OFFSET($W$53,0,(COLUMN()-COLUMN($AJ$4))*3,1,3)))+AL7,"") -> 0.5125523 | AN7: =IFERROR(IF(SUM(OFFSET($W$53,0,(COLUMN()-COLUMN($AJ$4))*3,1,3))=0,"",SUM(OFFSET($W$53,0,(COLUMN()-COLUMN($AJ$4))*3,1,3)))+AM7,"") | AO7: =IFERROR(IF(SUM(OFFSET($W$53,0,(COLUMN()-COLUMN($AJ$4))*3,1,3))=0,"",SUM(OFFSET($W$53,0,(COLUMN()-COLUMN($AJ$4))*3,1,3)))+AN7,"") | BA7: Ingredient System | BB7: 270 | BD7: Roti Quality Issue | BE7: 200
C8: Sep | D8: 350 | E8: 840 | F8: 3503 | G8: 0.099914359 | K8: Sep | L8: 319 | M8: 840 | N8: 5 | O8: 0.38571429 | R8: Qtr2 | S8: 1349 | T8: 0.011860638 | U8: 0.018532246 | AH8: Sep | AI8: 840 | AJ8: =IF(SUM(OFFSET($X$54,0,(COLUMN()-COLUMN($AJ$4))*3,1,3))=0,"",SUM(OFFSET($X$54,0,(COLUMN()-COLUMN($AJ$4))*3,1,3))) -> 0.12380952 | AK8: =IFERROR(IF(SUM(OFFSET($X$54,0,(COLUMN()-COLUMN($AJ$4))*3,1,3))=0,"",SUM(OFFSET($X$54,0,(COLUMN()-COLUMN($AJ$4))*3,1,3)))+AJ8,"") -> 0.29642857 | AL8: =IFERROR(IF(SUM(OFFSET($X$54,0,(COLUMN()-COLUMN($AJ$4))*3,1,3))=0,"",SUM(OFFSET($X$54,0,(COLUMN()-COLUMN($AJ$4))*3,1,3)))+AK8,"") -> 0.37261905 | AM8: =IFERROR(IF(SUM(OFFSET($X$54,0,(COLUMN()-COLUMN($AJ$4))*3,1,3))=0,"",SUM(OFFSET($X$54,0,(COLUMN()-COLUMN($AJ$4))*3,1,3)))+AL8,"") -> 0.41309524 | AN8: =IFERROR(IF(SUM(OFFSET($X$54,0,(COLUMN()-COLUMN($AJ$4))*3,1,3))=0,"",SUM(OFFSET($X$54,0,(COLUMN()-COLUMN($AJ$4))*3,1,3)))+AM8,"") | AO8: =IFERROR(IF(SUM(OFFSET($X$54,0,(COLUMN()-COLUMN($AJ$4))*3,1,3))=0,"",SUM(OFFSET($X$54,0,(COLUMN()-COLUMN($AJ$4))*3,1,3)))+AN8,"") | BA8: Heating/Cooking | BB8: 250 | BD8: Kicker Catcher Issue | BE8: 197
C9: Oct | D9: 233 | E9: 921 | F9: 4074 | G9: 0.057191949 | K9: Oct | L9: 258 | M9: 921 | N9: 9 | O9: 0.28990228 | R9: Qtr3 | S9: 0 | AH9: Oct | AI9: 921 | AJ9: =IF(SUM(OFFSET($Y$55,0,(COLUMN()-COLUMN($AJ$4))*3,1,3))=0,"",SUM(OFFSET($Y$55,0,(COLUMN()-COLUMN($AJ$4))*3,1,3))) -> 0.12269273 | AK9: =IFERROR(IF(SUM(OFFSET($Y$55,0,(COLUMN()-COLUMN($AJ$4))*3,1,3))=0,"",SUM(OFFSET($Y$55,0,(COLUMN()-COLUMN($AJ$4))*3,1,3)))+AJ9,"") -> 0.23018458 | AL9: =IFERROR(IF(SUM(OFFSET($Y$55,0,(COLUMN()-COLUMN($AJ$4))*3,1,3))=0,"",SUM(OFFSET($Y$55,0,(COLUMN()-COLUMN($AJ$4))*3,1,3)))+AK9,"") -> 0.28230185 | AM9: =IFERROR(IF(SUM(OFFSET($Y$55,0,(COLUMN()-COLUMN($AJ$4))*3,1,3))=0,"",SUM(OFFSET($Y$55,0,(COLUMN()-COLUMN($AJ$4))*3,1,3)))+AL9,"") -> 0.30944625 | AN9: =IFERROR(IF(SUM(OFFSET($Y$55,0,(COLUMN()-COLUMN($AJ$4))*3,1,3))=0,"",SUM(OFFSET($Y$55,0,(COLUMN()-COLUMN($AJ$4))*3,1,3)))+AM9,"") | AO9: =IFERROR(IF(SUM(OFFSET($Y$55,0,(COLUMN()-COLUMN($AJ$4))*3,1,3))=0,"",SUM(OFFSET($Y$55,0,(COLUMN()-COLUMN($AJ$4))*3,1,3)))+AN9,"") | BA9: Logistics | BB9: 236 | BD9: Kneader Blade Stuck | BE9: 175
C10: Nov | D10: 289 | E10: 1742 | F10: 5583 | G10: 0.051764284 | K10: Nov | L10: 391 | M10: 1742 | N10: 24 | O10: 0.23823192 | R10: Qtr4 | S10: 0 | AH10: Nov | AI10: 1742 | AJ10: =IF(SUM(OFFSET($Z$56,0,(COLUMN()-COLUMN($AJ$4))*3,1,3))=0,"",SUM(OFFSET($Z$56,0,(COLUMN()-COLUMN($AJ$4))*3,1,3))) -> 0.13605052 | AK10: =IFERROR(IF(SUM(OFFSET($Z$56,0,(COLUMN()-COLUMN($AJ$4))*3,1,3))=0,"",SUM(OFFSET($Z$56,0,(COLUMN()-COLUMN($AJ$4))*3,1,3)))+AJ10,"") -> 0.2238806 | AL10: =IFERROR(IF(SUM(OFFSET($Z$56,0,(COLUMN()-COLUMN($AJ$4))*3,1,3))=0,"",SUM(OFFSET($Z$56,0,(COLUMN()-COLUMN($AJ$4))*3,1,3)))+AK10,"") -> 0.28530425 | AM10: =IFERROR(IF(SUM(OFFSET($Z$56,0,(COLUMN()-COLUMN($AJ$4))*3,1,3))=0,"",SUM(OFFSET($Z$56,0,(COLUMN()-COLUMN($AJ$4))*3,1,3)))+AL10,"") | AN10: =IFERROR(IF(SUM(OFFSET($Z$56,0,(COLUMN()-COLUMN($AJ$4))*3,1,3))=0,"",SUM(OFFSET($Z$56,0,(COLUMN()-COLUMN($AJ$4))*3,1,3)))+AM10,"") | AO10: =IFERROR(IF(SUM(OFFSET($Z$56,0,(COLUMN()-COLUMN($AJ$4))*3,1,3))=0,"",SUM(OFFSET($Z$56,0,(COLUMN()-COLUMN($AJ$4))*3,1,3)))+AN10,"") | BA10: Press Pan Module | BB10: 166 | BD10: Cracked Machine | BE10: 139
C11: Dec | D11: 409 | E11: 2242 | F11: 7536 | G11: 0.054272824 | K11: Dec | L11: 360 | M11: 2242 | N11: 12 | O11: 0.16592328 | AH11: Dec | AI11: 2242 | AJ11: =IF(SUM(OFFSET($AA$57,0,(COLUMN()-COLUMN($AJ$4))*3,1,3))=0,"",SUM(OFFSET($AA$57,0,(COLUMN()-COLUMN($AJ$4))*3,1,3))) -> 0.13648528 | AK11: =IFERROR(IF(SUM(OFFSET($AA$57,0,(COLUMN()-COLUMN($AJ$4))*3,1,3))=0,"",SUM(OFFSET($AA$57,0,(COLUMN()-COLUMN($AJ$4))*3,1,3)))+AJ11,"") -> 0.18956289 | AL11: =IFERROR(IF(SUM(OFFSET($AA$57,0,(COLUMN()-COLUMN($AJ$4))*3,1,3))=0,"",SUM(OFFSET($AA$57,0,(COLUMN()-COLUMN($AJ$4))*3,1,3)))+AK11,"") -> 0.23104371 | AM11: =IFERROR(IF(SUM(OFFSET($AA$57,0,(COLUMN()-COLUMN($AJ$4))*3,1,3))=0,"",SUM(OFFSET($AA$57,0,(COLUMN()-COLUMN($AJ$4))*3,1,3)))+AL11,"") | AN11: =IFERROR(IF(SUM(OFFSET($AA$57,0,(COLUMN()-COLUMN($AJ$4))*3,1,3))=0,"",SUM(OFFSET($AA$57,0,(COLUMN()-COLUMN($AJ$4))*3,1,3)))+AM11,"") | AO11: =IFERROR(IF(SUM(OFFSET($AA$57,0,(COLUMN()-COLUMN($AJ$4))*3,1,3))=0,"",SUM(OFFSET($AA$57,0,(COLUMN()-COLUMN($AJ$4))*3,1,3)))+AN11,"") | BA11: Customer Service | BB11: 127 | BD11: Kneader Stuck | BE11: 120
B12: 2026 | C12: Jan | D12: 430 | E12: 278 | F12: 7405 | G12: 0.058068872 | J12: 2026 | K12: Jan | L12: 88 | M12: 278 | N12: 16 | O12: 0.37410072 | AG12: 2026 | AH12: Jan | AI12: 278 | AJ12: =IF(SUM(OFFSET($AB$58,0,(COLUMN()-COLUMN($AJ$4))*3,1,3))=0,"",SUM(OFFSET($AB$58,0,(COLUMN()-COLUMN($AJ$4))*3,1,3))) -> 0.04676259 | AK12: =IFERROR(IF(SUM(OFFSET($AB$58,0,(COLUMN()-COLUMN($AJ$4))*3,1,3))=0,"",SUM(OFFSET($AB$58,0,(COLUMN()-COLUMN($AJ$4))*3,1,3)))+AJ12,"") -> 0.28776978 | AL12: =IFERROR(IF(SUM(OFFSET($AB$58,0,(COLUMN()-COLUMN($AJ$4))*3,1,3))=0,"",SUM(OFFSET($AB$58,0,(COLUMN()-COLUMN($AJ$4))*3,1,3)))+AK12,"") -> 0.45683453 | AM12: =IFERROR(IF(SUM(OFFSET($AB$58,0,(COLUMN()-COLUMN($AJ$4))*3,1,3))=0,"",SUM(OFFSET($AB$58,0,(COLUMN()-COLUMN($AJ$4))*3,1,3)))+AL12,"") | AN12: =IFERROR(IF(SUM(OFFSET($AB$58,0,(COLUMN()-COLUMN($AJ$4))*3,1,3))=0,"",SUM(OFFSET($AB$58,0,(COLUMN()-COLUMN($AJ$4))*3,1,3)))+AM12,"") | AO12: =IFERROR(IF(SUM(OFFSET($AB$58,0,(COLUMN()-COLUMN($AJ$4))*3,1,3))=0,"",SUM(OFFSET($AB$58,0,(COLUMN()-COLUMN($AJ$4))*3,1,3)))+AN12,"") | BA12: VT Module | BB12: 65 | BD12: Press Pan Malfunction | BE12: 100
C13: Feb | D13: 395 | E13: 786 | F13: 7761 | G13: 0.050895503 | K13: Feb | L13: 112 | M13: 786 | N13: 21 | O13: 0.1692112 | AH13: Feb | AI13: 786 | AJ13: =IF(SUM(OFFSET($AC$59,0,(COLUMN()-COLUMN($AJ$4))*3,1,3))=0,"",SUM(OFFSET($AC$59,0,(COLUMN()-COLUMN($AJ$4))*3,1,3))) -> 0.063613232 | AK13: =IFERROR(IF(SUM(OFFSET($AC$59,0,(COLUMN()-COLUMN($AJ$4))*3,1,3))=0,"",SUM(OFFSET($AC$59,0,(COLUMN()-COLUMN($AJ$4))*3,1,3)))+AJ13,"") -> 0.18066158 | AL13: =IFERROR(IF(SUM(OFFSET($AC$59,0,(COLUMN()-COLUMN($AJ$4))*3,1,3))=0,"",SUM(OFFSET($AC$59,0,(COLUMN()-COLUMN($AJ$4))*3,1,3)))+AK13,"") | AM13: =IFERROR(IF(SUM(OFFSET($AC$59,0,(COLUMN()-COLUMN($AJ$4))*3,1,3))=0,"",SUM(OFFSET($AC$59,0,(COLUMN()-COLUMN($AJ$4))*3,1,3)))+AL13,"") | AN13: =IFERROR(IF(SUM(OFFSET($AC$59,0,(COLUMN()-COLUMN($AJ$4))*3,1,3))=0,"",SUM(OFFSET($AC$59,0,(COLUMN()-COLUMN($AJ$4))*3,1,3)))+AM13,"") | AO13: =IFERROR(IF(SUM(OFFSET($AC$59,0,(COLUMN()-COLUMN($AJ$4))*3,1,3))=0,"",SUM(OFFSET($AC$59,0,(COLUMN()-COLUMN($AJ$4))*3,1,3)))+AN13,"") | BA13: Grand Total | BB13: 3622 | BD13: Grand Total | BE13: 2740
C14: Mar | D14: 134 | E14: 598 | F14: 7964 | G14: 0.016825716 | K14: Mar | L14: 16 | M14: 598 | N14: 2 | O14: 0.030100334 | AH14: Mar | AI14: 598 | AJ14: =IF(SUM(OFFSET($AD$60,0,(COLUMN()-COLUMN($AJ$4))*3,1,3))=0,"",SUM(OFFSET($AD$60,0,(COLUMN()-COLUMN($AJ$4))*3,1,3))) -> 0.0050167224 | AK14: =IFERROR(IF(SUM(OFFSET($AD$60,0,(COLUMN()-COLUMN($AJ$4))*3,1,3))=0,"",SUM(OFFSET($AD$60,0,(COLUMN()-COLUMN($AJ$4))*3,1,3)))+AJ14,"") -> 0.033444816 | AL14: =IFERROR(IF(SUM(OFFSET($AD$60,0,(COLUMN()-COLUMN($AJ$4))*3,1,3))=0,"",SUM(OFFSET($AD$60,0,(COLUMN()-COLUMN($AJ$4))*3,1,3)))+AK14,"") | AM14: =IFERROR(IF(SUM(OFFSET($AD$60,0,(COLUMN()-COLUMN($AJ$4))*3,1,3))=0,"",SUM(OFFSET($AD$60,0,(COLUMN()-COLUMN($AJ$4))*3,1,3)))+AL14,"") | AN14: =IFERROR(IF(SUM(OFFSET($AD$60,0,(COLUMN()-COLUMN($AJ$4))*3,1,3))=0,"",SUM(OFFSET($AD$60,0,(COLUMN()-COLUMN($AJ$4))*3,1,3)))+AM14,"") | AO14: =IFERROR(IF(SUM(OFFSET($AD$60,0,(COLUMN()-COLUMN($AJ$4))*3,1,3))=0,"",SUM(OFFSET($AD$60,0,(COLUMN()-COLUMN($AJ$4))*3,1,3)))+AN14,"")
C15: Apr | D15: 205 | E15: 733 | F15: 8563 | G15: 0.023940208 | K15: Apr | L15: 17 | M15: 733 | N15: 1 | O15: 0.024556617 | AH15: Apr | AI15: 733 | AJ15: =IF(SUM(OFFSET($AE$61,0,(COLUMN()-COLUMN($AJ$4))*3,1,3))=0,"",SUM(OFFSET($AE$61,0,(COLUMN()-COLUMN($AJ$4))*3,1,3))) -> 0.021828104 | AK15: =IFERROR(IF(SUM(OFFSET($AE$61,0,(COLUMN()-COLUMN($AJ$4))*3,1,3))=0,"",SUM(OFFSET($AE$61,0,(COLUMN()-COLUMN($AJ$4))*3,1,3)))+AJ15,"") -> 0.039563438 | AL15: =IFERROR(IF(SUM(OFFSET($AE$61,0,(COLUMN()-COLUMN($AJ$4))*3,1,3))=0,"",SUM(OFFSET($AE$61,0,(COLUMN()-COLUMN($AJ$4))*3,1,3)))+AK15,"") | AM15: =IFERROR(IF(SUM(OFFSET($AE$61,0,(COLUMN()-COLUMN($AJ$4))*3,1,3))=0,"",SUM(OFFSET($AE$61,0,(COLUMN()-COLUMN($AJ$4))*3,1,3)))+AL15,"") | AN15: =IFERROR(IF(SUM(OFFSET($AE$61,0,(COLUMN()-COLUMN($AJ$4))*3,1,3))=0,"",SUM(OFFSET($AE$61,0,(COLUMN()-COLUMN($AJ$4))*3,1,3)))+AM15,"") | AO15: =IFERROR(IF(SUM(OFFSET($AE$61,0,(COLUMN()-COLUMN($AJ$4))*3,1,3))=0,"",SUM(OFFSET($AE$61,0,(COLUMN()-COLUMN($AJ$4))*3,1,3)))+AN15,"")
C16: May | D16: 148 | E16: 616 | F16: 8974 | G16: 0.016492088
C17: Jun | D17: 113 | E17: 0 | F17: 8826 | G17: 0.012803082
C18: Jul | D18: 298 | E18: 0 | F18: 8713 | G18: 0.034201767
Q47: Cumulative Manufacturing Cohort Heatmap
Q48: Year | R48: Month | S48: Delivered Units | T48: 2025 | AB48: 2026
T49: May | U49: Jun | V49: Jul | W49: Aug | X49: Sep | Y49: Oct | Z49: Nov | AA49: Dec | AB49: Jan | AC49: Feb | AD49: Mar | AE49: Apr | AF49: May | AG49: Jun | AH49: Jul | AI49: Aug | AJ49: Sep | AK49: Oct | AL49: Nov | AM49: Dec
Q50: 2025 | R50: May | S50: 138 | T50: =IF(IFERROR(PIV!D19/PIV!$T19,"")=0,"",IFERROR(PIV!D19/PIV!$T19,"")) -> 0.0072463768 | U50: =IF(IFERROR(PIV!E19/PIV!$T19,"")=0,"",IFERROR(PIV!E19/PIV!$T19,"")) -> 0.13043478 | V50: =IF(IFERROR(PIV!F19/PIV!$T19,"")=0,"",IFERROR(PIV!F19/PIV!$T19,"")) -> 0.14492754 | W50: =IF(IFERROR(PIV!G19/PIV!$T19,"")=0,"",IFERROR(PIV!G19/PIV!$T19,"")) -> 0.11594203 | X50: =IF(IFERROR(PIV!H19/PIV!$T19,"")=0,"",IFERROR(PIV!H19/PIV!$T19,"")) -> 0.10869565 | Y50: =IF(IFERROR(PIV!I19/PIV!$T19,"")=0,"",IFERROR(PIV!I19/PIV!$T19,"")) -> 0.036231884 | Z50: =IF(IFERROR(PIV!J19/PIV!$T19,"")=0,"",IFERROR(PIV!J19/PIV!$T19,"")) -> 0.057971014 | AA50: =IF(IFERROR(PIV!K19/PIV!$T19,"")=0,"",IFERROR(PIV!K19/PIV!$T19,"")) -> 0.057971014 | ... AH50: =IF(IFERROR(PIV!R19/PIV!$T19,"")=0,"",IFERROR(PIV!R19/PIV!$T19,"")) -> 0.028985507
R51: Jun | S51: 1004 | T51: =IF(IFERROR(PIV!D20/PIV!$T20,"")=0,"",IFERROR(PIV!D20/PIV!$T20,"")) | U51: =IF(IFERROR(PIV!E20/PIV!$T20,"")=0,"",IFERROR(PIV!E20/PIV!$T20,"")) -> 0.022908367 | V51: =IF(IFERROR(PIV!F20/PIV!$T20,"")=0,"",IFERROR(PIV!F20/PIV!$T20,"")) -> 0.087649402 | W51: =IF(IFERROR(PIV!G20/PIV!$T20,"")=0,"",IFERROR(PIV!G20/PIV!$T20,"")) -> 0.083665339 | X51: =IF(IFERROR(PIV!H20/PIV!$T20,"")=0,"",IFERROR(PIV!H20/PIV!$T20,"")) -> 0.098605578 | Y51: =IF(IFERROR(PIV!I20/PIV!$T20,"")=0,"",IFERROR(PIV!I20/PIV!$T20,"")) -> 0.052788845 | Z51: =IF(IFERROR(PIV!J20/PIV!$T20,"")=0,"",IFERROR(PIV!J20/PIV!$T20,"")) -> 0.049800797 | AA51: =IF(IFERROR(PIV!K20/PIV!$T20,"")=0,"",IFERROR(PIV!K20/PIV!$T20,"")) -> 0.046812749 | ... AH51: =IF(IFERROR(PIV!R20/PIV!$T20,"")=0,"",IFERROR(PIV!R20/PIV!$T20,"")) -> 0.020916335
R52: Jul | S52: 1081 | T52: =IF(IFERROR(PIV!D21/PIV!$T21,"")=0,"",IFERROR(PIV!D21/PIV!$T21,"")) | U52: =IF(IFERROR(PIV!E21/PIV!$T21,"")=0,"",IFERROR(PIV!E21/PIV!$T21,"")) -> 0.00092506938 | V52: =IF(IFERROR(PIV!F21/PIV!$T21,"")=0,"",IFERROR(PIV!F21/PIV!$T21,"")) -> 0.026827012 | W52: =IF(IFERROR(PIV!G21/PIV!$T21,"")=0,"",IFERROR(PIV!G21/PIV!$T21,"")) -> 0.07493062 | X52: =IF(IFERROR(PIV!H21/PIV!$T21,"")=0,"",IFERROR(PIV!H21/PIV!$T21,"")) -> 0.098057354 | Y52: =IF(IFERROR(PIV!I21/PIV!$T21,"")=0,"",IFERROR(PIV!I21/PIV!$T21,"")) -> 0.048103608 | Z52: =IF(IFERROR(PIV!J21/PIV!$T21,"")=0,"",IFERROR(PIV!J21/PIV!$T21,"")) -> 0.054579093 | AA52: =IF(IFERROR(PIV!K21/PIV!$T21,"")=0,"",IFERROR(PIV!K21/PIV!$T21,"")) -> 0.063829787 | ... AH52: =IF(IFERROR(PIV!R21/PIV!$T21,"")=0,"",IFERROR(PIV!R21/PIV!$T21,"")) -> 0.027752081
R53: Aug | S53: 956 | T53: =IF(IFERROR(PIV!D22/PIV!$T22,"")=0,"",IFERROR(PIV!D22/PIV!$T22,"")) | U53: =IF(IFERROR(PIV!E22/PIV!$T22,"")=0,"",IFERROR(PIV!E22/PIV!$T22,"")) | V53: =IF(IFERROR(PIV!F22/PIV!$T22,"")=0,"",IFERROR(PIV!F22/PIV!$T22,"")) -> 0.0010460251 | W53: =IF(IFERROR(PIV!G22/PIV!$T22,"")=0,"",IFERROR(PIV!G22/PIV!$T22,"")) -> 0.0083682008 | X53: =IF(IFERROR(PIV!H22/PIV!$T22,"")=0,"",IFERROR(PIV!H22/PIV!$T22,"")) -> 0.10041841 | Y53: =IF(IFERROR(PIV!I22/PIV!$T22,"")=0,"",IFERROR(PIV!I22/PIV!$T22,"")) -> 0.074267782 | Z53: =IF(IFERROR(PIV!J22/PIV!$T22,"")=0,"",IFERROR(PIV!J22/PIV!$T22,"")) -> 0.065899582 | AA53: =IF(IFERROR(PIV!K22/PIV!$T22,"")=0,"",IFERROR(PIV!K22/PIV!$T22,"")) -> 0.067991632 | ... AH53: =IF(IFERROR(PIV!R22/PIV!$T22,"")=0,"",IFERROR(PIV!R22/PIV!$T22,"")) -> 0.028242678
R54: Sep | S54: 840 | T54: =IF(IFERROR(PIV!D23/PIV!$T23,"")=0,"",IFERROR(PIV!D23/PIV!$T23,"")) | U54: =IF(IFERROR(PIV!E23/PIV!$T23,"")=0,"",IFERROR(PIV!E23/PIV!$T23,"")) | V54: =IF(IFERROR(PIV!F23/PIV!$T23,"")=0,"",IFERROR(PIV!F23/PIV!$T23,"")) | W54: =IF(IFERROR(PIV!G23/PIV!$T23,"")=0,"",IFERROR(PIV!G23/PIV!$T23,"")) | X54: =IF(IFERROR(PIV!H23/PIV!$T23,"")=0,"",IFERROR(PIV!H23/PIV!$T23,"")) -> 0.013095238 | Y54: =IF(IFERROR(PIV!I23/PIV!$T23,"")=0,"",IFERROR(PIV!I23/PIV!$T23,"")) -> 0.047619048 | Z54: =IF(IFERROR(PIV!J23/PIV!$T23,"")=0,"",IFERROR(PIV!J23/PIV!$T23,"")) -> 0.063095238 | AA54: =IF(IFERROR(PIV!K23/PIV!$T23,"")=0,"",IFERROR(PIV!K23/PIV!$T23,"")) -> 0.067857143 | ... AH54: =IF(IFERROR(PIV!R23/PIV!$T23,"")=0,"",IFERROR(PIV!R23/PIV!$T23,"")) -> 0.026190476
R55: Oct | S55: 921 | T55: =IF(IFERROR(PIV!D24/PIV!$T24,"")=0,"",IFERROR(PIV!D24/PIV!$T24,"")) | U55: =IF(IFERROR(PIV!E24/PIV!$T24,"")=0,"",IFERROR(PIV!E24/PIV!$T24,"")) | V55: =IF(IFERROR(PIV!F24/PIV!$T24,"")=0,"",IFERROR(PIV!F24/PIV!$T24,"")) | W55: =IF(IFERROR(PIV!G24/PIV!$T24,"")=0,"",IFERROR(PIV!G24/PIV!$T24,"")) | X55: =IF(IFERROR(PIV!H24/PIV!$T24,"")=0,"",IFERROR(PIV!H24/PIV!$T24,"")) -> 0.0010857763 | Y55: =IF(IFERROR(PIV!I24/PIV!$T24,"")=0,"",IFERROR(PIV!I24/PIV!$T24,"")) -> 0.0021715527 | Z55: =IF(IFERROR(PIV!J24/PIV!$T24,"")=0,"",IFERROR(PIV!J24/PIV!$T24,"")) -> 0.045602606 | AA55: =IF(IFERROR(PIV!K24/PIV!$T24,"")=0,"",IFERROR(PIV!K24/PIV!$T24,"")) -> 0.074918567 | ... AH55: =IF(IFERROR(PIV!R24/PIV!$T24,"")=0,"",IFERROR(PIV!R24/PIV!$T24,"")) -> 0.027144408
R56: Nov | S56: 1742 | T56: =IF(IFERROR(PIV!D25/PIV!$T25,"")=0,"",IFERROR(PIV!D25/PIV!$T25,"")) | U56: =IF(IFERROR(PIV!E25/PIV!$T25,"")=0,"",IFERROR(PIV!E25/PIV!$T25,"")) | V56: =IF(IFERROR(PIV!F25/PIV!$T25,"")=0,"",IFERROR(PIV!F25/PIV!$T25,"")) | W56: =IF(IFERROR(PIV!G25/PIV!$T25,"")=0,"",IFERROR(PIV!G25/PIV!$T25,"")) | X56: =IF(IFERROR(PIV!H25/PIV!$T25,"")=0,"",IFERROR(PIV!H25/PIV!$T25,"")) | Y56: =IF(IFERROR(PIV!I25/PIV!$T25,"")=0,"",IFERROR(PIV!I25/PIV!$T25,"")) | Z56: =IF(IFERROR(PIV!J25/PIV!$T25,"")=0,"",IFERROR(PIV!J25/PIV!$T25,"")) -> 0.0028702641 | AA56: =IF(IFERROR(PIV!K25/PIV!$T25,"")=0,"",IFERROR(PIV!K25/PIV!$T25,"")) -> 0.082663605 | ... AH56: =IF(IFERROR(PIV!R25/PIV!$T25,"")=0,"",IFERROR(PIV!R25/PIV!$T25,"")) -> 0.022962113
R57: Dec | S57: 2242 | T57: =IF(IFERROR(PIV!D26/PIV!$T26,"")=0,"",IFERROR(PIV!D26/PIV!$T26,"")) | U57: =IF(IFERROR(PIV!E26/PIV!$T26,"")=0,"",IFERROR(PIV!E26/PIV!$T26,"")) | V57: =IF(IFERROR(PIV!F26/PIV!$T26,"")=0,"",IFERROR(PIV!F26/PIV!$T26,"")) | W57: =IF(IFERROR(PIV!G26/PIV!$T26,"")=0,"",IFERROR(PIV!G26/PIV!$T26,"")) | X57: =IF(IFERROR(PIV!H26/PIV!$T26,"")=0,"",IFERROR(PIV!H26/PIV!$T26,"")) | Y57: =IF(IFERROR(PIV!I26/PIV!$T26,"")=0,"",IFERROR(PIV!I26/PIV!$T26,"")) | Z57: =IF(IFERROR(PIV!J26/PIV!$T26,"")=0,"",IFERROR(PIV!J26/PIV!$T26,"")) | AA57: =IF(IFERROR(PIV!K26/PIV!$T26,"")=0,"",IFERROR(PIV!K26/PIV!$T26,"")) -> 0.005352364 | ... AH57: =IF(IFERROR(PIV!R26/PIV!$T26,"")=0,"",IFERROR(PIV!R26/PIV!$T26,"")) -> 0.023639607
Q58: 2026 | R58: Jan | S58: 278 | T58: =IF(IFERROR(PIV!D27/PIV!$T27,"")=0,"",IFERROR(PIV!D27/PIV!$T27,"")) | U58: =IF(IFERROR(PIV!E27/PIV!$T27,"")=0,"",IFERROR(PIV!E27/PIV!$T27,"")) | V58: =IF(IFERROR(PIV!F27/PIV!$T27,"")=0,"",IFERROR(PIV!F27/PIV!$T27,"")) | W58: =IF(IFERROR(PIV!G27/PIV!$T27,"")=0,"",IFERROR(PIV!G27/PIV!$T27,"")) | X58: =IF(IFERROR(PIV!H27/PIV!$T27,"")=0,"",IFERROR(PIV!H27/PIV!$T27,"")) | Y58: =IF(IFERROR(PIV!I27/PIV!$T27,"")=0,"",IFERROR(PIV!I27/PIV!$T27,"")) | Z58: =IF(IFERROR(PIV!J27/PIV!$T27,"")=0,"",IFERROR(PIV!J27/PIV!$T27,"")) | AA58: =IF(IFERROR(PIV!K27/PIV!$T27,"")=0,"",IFERROR(PIV!K27/PIV!$T27,"")) | ... AH58: =IF(IFERROR(PIV!R27/PIV!$T27,"")=0,"",IFERROR(PIV!R27/PIV!$T27,"")) -> 0.16906475
R59: Feb | S59: 786 | T59: =IF(IFERROR(PIV!D28/PIV!$T28,"")=0,"",IFERROR(PIV!D28/PIV!$T28,"")) | U59: =IF(IFERROR(PIV!E28/PIV!$T28,"")=0,"",IFERROR(PIV!E28/PIV!$T28,"")) | V59: =IF(IFERROR(PIV!F28/PIV!$T28,"")=0,"",IFERROR(PIV!F28/PIV!$T28,"")) | W59: =IF(IFERROR(PIV!G28/PIV!$T28,"")=0,"",IFERROR(PIV!G28/PIV!$T28,"")) | X59: =IF(IFERROR(PIV!H28/PIV!$T28,"")=0,"",IFERROR(PIV!H28/PIV!$T28,"")) | Y59: =IF(IFERROR(PIV!I28/PIV!$T28,"")=0,"",IFERROR(PIV!I28/PIV!$T28,"")) | Z59: =IF(IFERROR(PIV!J28/PIV!$T28,"")=0,"",IFERROR(PIV!J28/PIV!$T28,"")) | AA59: =IF(IFERROR(PIV!K28/PIV!$T28,"")=0,"",IFERROR(PIV!K28/PIV!$T28,"")) | ... AH59: =IF(IFERROR(PIV!R28/PIV!$T28,"")=0,"",IFERROR(PIV!R28/PIV!$T28,"")) -> 0.058524173
R60: Mar | S60: 598 | T60: =IF(IFERROR(PIV!D29/PIV!$T29,"")=0,"",IFERROR(PIV!D29/PIV!$T29,"")) | U60: =IF(IFERROR(PIV!E29/PIV!$T29,"")=0,"",IFERROR(PIV!E29/PIV!$T29,"")) | V60: =IF(IFERROR(PIV!F29/PIV!$T29,"")=0,"",IFERROR(PIV!F29/PIV!$T29,"")) | W60: =IF(IFERROR(PIV!G29/PIV!$T29,"")=0,"",IFERROR(PIV!G29/PIV!$T29,"")) | X60: =IF(IFERROR(PIV!H29/PIV!$T29,"")=0,"",IFERROR(PIV!H29/PIV!$T29,"")) | Y60: =IF(IFERROR(PIV!I29/PIV!$T29,"")=0,"",IFERROR(PIV!I29/PIV!$T29,"")) | Z60: =IF(IFERROR(PIV!J29/PIV!$T29,"")=0,"",IFERROR(PIV!J29/PIV!$T29,"")) | AA60: =IF(IFERROR(PIV!K29/PIV!$T29,"")=0,"",IFERROR(PIV!K29/PIV!$T29,"")) | ... AH60: =IF(IFERROR(PIV!R29/PIV!$T29,"")=0,"",IFERROR(PIV!R29/PIV!$T29,"")) -> 0.016722408
R61: Apr | S61: 733 | T61: =IF(IFERROR(PIV!D30/PIV!$T30,"")=0,"",IFERROR(PIV!D30/PIV!$T30,"")) | U61: =IF(IFERROR(PIV!E30/PIV!$T30,"")=0,"",IFERROR(PIV!E30/PIV!$T30,"")) | V61: =IF(IFERROR(PIV!F30/PIV!$T30,"")=0,"",IFERROR(PIV!F30/PIV!$T30,"")) | W61: =IF(IFERROR(PIV!G30/PIV!$T30,"")=0,"",IFERROR(PIV!G30/PIV!$T30,"")) | X61: =IF(IFERROR(PIV!H30/PIV!$T30,"")=0,"",IFERROR(PIV!H30/PIV!$T30,"")) | Y61: =IF(IFERROR(PIV!I30/PIV!$T30,"")=0,"",IFERROR(PIV!I30/PIV!$T30,"")) | Z61: =IF(IFERROR(PIV!J30/PIV!$T30,"")=0,"",IFERROR(PIV!J30/PIV!$T30,"")) | AA61: =IF(IFERROR(PIV!K30/PIV!$T30,"")=0,"",IFERROR(PIV!K30/PIV!$T30,"")) | ... AH61: =IF(IFERROR(PIV!R30/PIV!$T30,"")=0,"",IFERROR(PIV!R30/PIV!$T30,"")) -> 0.017735334

Sheet Delivered MC
A1: Delviered Date | B1: Delivered Year | C1: Delivered Month | D1: Delivered RMA Count
A2: =DATE(B2,MONTH(1&C2),1) -> 45778 | B2: 2025 | C2: May | D2: 138
A3: =DATE(B3,MONTH(1&C3),1) -> 45809 | B3: 2025 | C3: Jun | D3: 1004
A4: =DATE(B4,MONTH(1&C4),1) -> 45839 | B4: 2025 | C4: Jul | D4: 1081
A5: =DATE(B5,MONTH(1&C5),1) -> 45870 | B5: 2025 | C5: Aug | D5: 956
A6: =DATE(B6,MONTH(1&C6),1) -> 45901 | B6: 2025 | C6: Sep | D6: 840
A7: =DATE(B7,MONTH(1&C7),1) -> 45931 | B7: 2025 | C7: Oct | D7: 921
A8: =DATE(B8,MONTH(1&C8),1) -> 45962 | B8: 2025 | C8: Nov | D8: 1742
A9: =DATE(B9,MONTH(1&C9),1) -> 45992 | B9: 2025 | C9: Dec | D9: 2242
A10: =DATE(B10,MONTH(1&C10),1) -> 46023 | B10: 2026 | C10: Jan | D10: 278
A11: =DATE(B11,MONTH(1&C11),1) -> 46054 | B11: 2026 | C11: Feb | D11: 786
A12: =DATE(B12,MONTH(1&C12),1) -> 46082 | B12: 2026 | C12: Mar | D12: 598
A13: =DATE(B13,MONTH(1&C13),1) -> 46113 | B13: 2026 | C13: Apr | D13: 733
... A21: =DATE(B21,MONTH(1&C21),1) -> 46357 | B21: 2026 | C21: Dec | D21: 0

Sheet Odoo_Combined
A1: Issue Reported Date | B1: Customer's Name | C1: Order# | D1: MachineSerialNumber | E1: Replacement Type | F1: Roti Count | G1: Return Type | H1: Replacement SO | I1: Request Month | J1: Year | K1: Failure.Keyword | L1: Failure.Failure Mode | M1: Failure.Failure Category | N1: Shipment Month | O1: Shipped Year | P1: CA/ME | Q1: WW Code | R1: MC Type | S1: RMA Lines | T1: Status | U1: Fee Amount | V1: Is Shipment Initiated | W1: SO Return Status | X1: Roti Count Group
A2: 46237 | B2: Sujith Vijaya Kumar | C2: 74081 | D2: ZM1251250CAW06644 | E2: Machine | F2: 875 | G2: Replacement | H2: RSO09356 | I2: Aug | J2: 2026 | K2: KNEADING TRAY STUCK | L2: Kneader Stuck | M2: Kneader | N2: Dec | O2: 2025 | P2: CA | Q2: 50 | R2: RNext | S2: [ZNF0111AW-CA] Rotimatic Next (Black & White) | T2: Processing | U2: 40 | V2: 1 | W2: Return with Refund/Replacement | X2: 500–999
A3: 46237 | B3: Shalaka Sawant | C3: 75980 | D3: ZM1251251CAG07710 | E3: Machine | F3: 116 | G3: Replacement | H3: RSO09355 | I3: Aug | J3: 2026 | K3: TRANSFER ARM RATTLING NOISE | L3: Kicker Noise | M3: Kicker Module | N3: Dec | O3: 2025 | P3: CA | Q3: 51 | R3: RNext | S3: [ZNF0111AG-CA] Rotimatic Next (Black & Grey) | T3: Processing | U3: 0 | V3: 1 | W3: Return with Refund/Replacement | X3: 50–499
A4: 46237 | B4: Neel Shah | C4: RSO03202 | D4: ZM1250729CAG01563 | E4: Machine | F4: 0 | G4: Replacement | H4: RSO09354 | I4: Aug | J4: 2026 | K4: KNEADER BLADE STUCK | L4: Kneader Blade Stuck | M4: Kneader | N4: Jul | O4: 2025 | P4: CA | Q4: 29 | R4: RNext | S4: [ZNF0111AG-CA] Rotimatic Next (Black & Grey) | T4: Processing | U4: 0 | V4: 1 | W4: Return with Refund/Replacement | X4: 0–49
A5: 46237 | B5: Owais Ahmed | C5: RSO05154 | D5: ZM1251146MEG01650 | E5: Machine | F5: 963 | G5: Replacement | H5: RSO09353 | I5: Aug | J5: 2026 | K5: CANNOT TRANSFER DOUGH BALL | L5: Kicker Drive | M5: Kicker Module | N5: Nov | O5: 2025 | P5: ME | Q5: 46 | R5: RNext | S5: [ZNF0111AG-ME] Rotimatic Next (Black & Grey) | T5: Processing | U5: 0 | V5: 1 | W5: Return with Refund/Replacement | X5: 500–999
A6: 46237 | B6: Saurabh Brahmbhatt | C6: 41090 | D6: ZM82308CAB139 | E6: Machine | F6: 8500 | G6: Replacement | H6: RSO09352 | I6: Aug | J6: 2026 | N6: Aug | O6: 2023 | P6: B1 | Q6: CA | R6: RPlus | S6: [ZMA0111A-CA] Rotimatic Plus | T6: Processing | U6: 0 | V6: 1 | W6: Return with Refund/Replacement | X6: 5,000+
A7: 46237 | B7: Pranjal Jain | C7: RSO04838 | D7: ZM1251144CAW04488 | E7: Machine | F7: 609 | G7: Replacement | H7: RSO09351 | I7: Aug | J7: 2026 | K7: NOT POWERING ON | L7: Not Powering On | M7: Electrical | N7: Nov | O7: 2025 | P7: CA | Q7: 44 | R7: RNext | S7: [ZNF0111AW-CA] Rotimatic Next (Black & White) | T7: Processing | U7: 0 | V7: 1 | W7: Return with Refund/Replacement | X7: 500–999
A8: 46234 | B8: Ashish Mehta | C8: 78106 | D8: ZM1260102CAG08113 | E8: Machine | F8: 433 | G8: Replacement | H8: RSO09350 | I8: Jul | J8: 2026 | K8: NOT POWERING ON | L8: Not Powering On | M8: Electrical | N8: Jan | O8: 2026 | P8: CA | Q8: 02 | R8: RNext | S8: [ZNF0111AG-CA] Rotimatic Next (Black & Grey) | T8: Processing | U8: 0 | V8: 1 | W8: Return with Refund/Replacement | X8: 50–499
A9: 46234 | B9: Rohit Yadav | C9: 62977 | D9: ZM1250416CAG00186 | E9: Machine | F9: 712 | G9: Replacement | H9: RSO09349 | I9: Jul | J9: 2026 | K9: TRANSFER ARM STUCK | L9: Kicker Drive | M9: Kicker Module | N9: Apr | O9: 2025 | P9: CA | Q9: 16 | R9: RNext | S9: [ZMA0111A-CA] Rotimatic Plus | T9: Processing | U9: 0 | V9: 1 | W9: Return with Refund/Replacement | X9: 500–999
A10: 46234 | B10: Brigade People Pty Ltd | C10: 68935 | D10: ZM1250835MEW00868 | E10: Machine | F10: 0 | G10: Replacement | H10: RSO09348 | I10: Jul | J10: 2026 | K10: KNEADER BLADE STUCK | L10: Kneader Blade Stuck | M10: Kneader | N10: Aug | O10: 2025 | P10: ME | Q10: 35 | R10: RNext | S10: [ZNF0111AW-ME] Rotimatic Next (Black & White) | T10: Processing | U10: 172 | V10: 1 | W10: Return with Refund/Replacement | X10: 0–49
A11: 46234 | B11: sateesh vadde | C11: 71143 | D11: ZM1251043CAG03935 | E11: Machine | F11: 0 | G11: Replacement | H11: RSO09347 | I11: Jul | J11: 2026 | K11: TRANSFER ARM STUCK | L11: Kicker Drive | M11: Kicker Module | N11: Oct | O11: 2025 | P11: CA | Q11: 43 | R11: RNext | S11: [ZNF0111AG-CA] Rotimatic Next (Black & Grey) | T11: Processing | U11: 211 | V11: 1 | W11: Return with Refund/Replacement | X11: 0–49
A12: 46234 | B12: Ashleye Soanes | C12: 80569 | D12: ZM1260311CAW09995 | E12: Machine | F12: 0 | G12: Replacement | H12: RSO09346 | I12: Jul | J12: 2026 | K12: TRANSFER ARM STUCK | L12: Kicker Drive | M12: Kicker Module | N12: Mar | O12: 2026 | P12: CA | Q12: 11 | R12: RNext | S12: [ZNF0111AW-CA] Rotimatic Next (Black & White) | T12: Processing | U12: 54 | V12: 1 | W12: Return with Refund/Replacement | X12: 0–49
A13: 46234 | B13: varun_varmani@hotmail.com | C13: 76496 | D13: ZM1260209MEG03101 | E13: Machine | F13: 0 | G13: Replacement | H13: RSO09345 | I13: Jul | J13: 2026 | K13: TRANSFER ARM STUCK | L13: Kicker Drive | M13: Kicker Module | N13: Feb | O13: 2026 | P13: ME | Q13: 09 | R13: RNext | S13: [2YearRotimaticNextRotimaticCareWarranty] Rotimatic Next - Rotimatic Care Plus Warranty - 2 Years | T13: Processing | U13: 125 | V13: 1 | W13: Return with Refund/Replacement | X13: 0–49
A14: 46234 | B14: Rajesh Ganta | C14: 80144 | D14: ZM1260208CAG09747 | E14: Machine | F14: 0 | G14: Replacement | H14: RSO09344 | I14: Jul | J14: 2026 | K14: NOT POWERING ON | L14: Not Powering On | M14: Electrical | N14: Feb | O14: 2026 | P14: CA | Q14: 08 | R14: RNext | S14: [ZNF0111AG-CA] Rotimatic Next (Black & Grey) | T14: Processing | U14: 40 | V14: 1 | W14: Return with Refund/Replacement | X14: 0–49
A15: 46234 | B15: Pratik Pradhan | C15: 77473 | D15: ZM1260209MEG02955 | E15: Machine | F15: 0 | G15: Replacement | H15: RSO09343 | I15: Jul | J15: 2026 | K15: RATTLING NOISE | L15: Rattling Noise | M15: Kicker Module | N15: Feb | O15: 2026 | P15: ME | Q15: 09 | R15: RNext | S15: [ZNF0111AG-ME] Rotimatic Next (Black & Grey) | T15: Processing | U15: 0 | V15: 1 | W15: Return with Refund/Replacement | X15: 0–49
A16: 46234 | B16: Ashwanth Sivankutty Nair | C16: 69496 | D16: ZM1250836CAG02766 | E16: Machine | F16: 0 | G16: Replacement | H16: RSO09342 | I16: Jul | J16: 2026 | N16: Aug | O16: 2025 | P16: CA | Q16: 36 | R16: RNext | S16: [1YearRotimaticNextRotimaticCareWarranty] Rotimatic Next - Rotimatic Care Plus Warranty - 1 Year | T16: Processing | U16: 41 | V16: 1 | W16: Return with Refund/Replacement | X16: 0–49
A17: 46234 | B17: Sunmeet Singh | C17: RSO05345 | D17: ZM1251146MEG01682 | E17: Machine | F17: 0 | G17: Replacement | H17: RSO09341 | I17: Jul | J17: 2026 | K17: PRESS PAN STUCK | L17: Press Pan Malfunction | M17: Press Pan Module | N17: Nov | O17: 2025 | P17: ME | Q17: 46 | R17: RNext | S17: [ZNF0111AG-ME] Rotimatic Next (Black & Grey) | T17: Processing | U17: 0 | V17: 1 | W17: Return with Refund/Replacement | X17: 0–49
A18: 46234 | B18: Sunita Khara | C18: 78487 | D18: ZM1260209CAW09903 | E18: Machine | F18: 0 | G18: Replacement | H18: RSO09340 | I18: Jul | J18: 2026 | K18: NOT POWERING ON | L18: Not Powering On | M18: Electrical | N18: Feb | O18: 2026 | P18: CA | Q18: 09 | R18: RNext | S18: [ZNF0111AW-CA] Rotimatic Next (Black & White) | T18: Processing | U18: 40 | V18: 1 | W18: Return with Refund/Replacement | X18: 0–49
A19: 46234 | B19: Munish Minocha | C19: 79729 | D19: ZM1260311CAW09988 | E19: Machine | F19: 0 | G19: Replacement | H19: RSO09339 | I19: Jul | J19: 2026 | K19: NOT POWERING ON | L19: Not Powering On | M19: Electrical | N19: Mar | O19: 2026 | P19: CA | Q19: 11 | R19: RNext | S19: [ZNF0111AW-CA] Rotimatic Next (Black & White) | T19: Processing | U19: 48 | V19: 1 | W19: Return with Refund/Replacement | X19: 0–49
A20: 46233 | B20: vidhi modi | C20: 70306 | D20: ZM1251043CAG03932 | G20: Refund with Return | I20: Jul | J20: 2026 | K20: NOT POWERING ON | L20: Not Powering On | M20: Electrical | N20: Oct | O20: 2025 | P20: CA | Q20: 43 | R20: RNext | S20: [6MonthsRotimaticNextRotimaticCareWarranty] Rotimatic Next - Rotimatic Care Plus Warranty - 6 Months | T20: Submitted | U20: 0 | V20: 1 | W20: Cancellation
A21: 46233 | B21: Sayali Autade | C21: 74763 | D21: ZM1251250CAW06779 | E21: Machine | F21: 1914 | G21: Replacement | H21: RSO09338 | I21: Jul | J21: 2026 | K21: KNEADING TRAY STUCK | L21: Kneader Stuck | M21: Kneader | N21: Dec | O21: 2025 | P21: CA | Q21: 50 | R21: RNext | S21: [2YearRotimaticNextRotimaticCareWarranty] Rotimatic Next - Rotimatic Care Plus Warranty - 2 Years | T21: Processing | U21: 40 | V21: 1 | W21: Return with Refund/Replacement | X21: 1,000–1,999
A22: 46233 | B22: Alakh Biniwale | C22: 71777 | D22: ZM1251146CAG04887 | E22: Machine | F22: 0 | G22: Replacement | H22: RSO09337 | I22: Jul | J22: 2026 | K22: TOP CASING CRACK | L22: Cracked Machine | M22: Logistics | N22: Nov | O22: 2025 | P22: CA | Q22: 46 | R22: RNext | S22: [3YearRotimaticNextRotimaticCareWarranty] Rotimatic Next - Rotimatic Care Plus Warranty - 3 Years | T22: Processing | U22: 63 | V22: 1 | W22: Return with Refund/Replacement | X22: 0–49
A23: 46233 | B23: Anmol Singh | C23: RSO04577 | D23: ZM1250940CAW03285 | E23: Machine | F23: 0 | G23: Replacement | H23: RSO09336 | I23: Jul | J23: 2026 | K23: NOT POWERING ON | L23: Not Powering On | M23: Electrical | N23: Sep | O23: 2025 | P23: CA | Q23: 40 | R23: RNext | S23: [ZNF0111AG-CA] Rotimatic Next (Black & Grey) | T23: Processing | U23: 0 | V23: 1 | W23: Return with Refund/Replacement | X23: 0–49
A24: 46232 | B24: Shipra Singh | C24: RSO05912 | D24: ZM1251250CAW06647 | E24: Machine | F24: 48 | G24: Replacement | H24: RSO09335 | I24: Jul | J24: 2026 | N24: Dec | O24: 2025 | P24: CA | Q24: 50 | R24: RNext | S24: [ZNF0111AW-CA] Rotimatic Next (Black & White) | T24: Processing | U24: 0 | V24: 1 | W24: Return with Refund/Replacement | X24: 0–49
A25: 46232 | B25: Ajay Sekhri | C25: 64218 | D25: ZM1250626CAW01396 | E25: Machine | F25: 230 | G25: Replacement | H25: RSO09334 | I25: Jul | J25: 2026 | K25: KNEADING TRAY STUCK | L25: Kneader Stuck | M25: Kneader | N25: Jun | O25: 2025 | P25: CA | Q25: 26 | R25: RNext | S25: [3YearRotimaticNextRotimaticCareWarranty] Rotimatic Next - Rotimatic Care Plus Warranty - 3 Years | T25: Processing | U25: 0 | V25: 1 | W25: Return with Refund/Replacement | X25: 50–499
A26: 46232 | B26: Abhishek Dhoundiyal | C26: RSO08422 | D26: ZM1260417CAG10464 | E26: Machine | F26: 305 | G26: Replacement | H26: RSO09333 | I26: Jul | J26: 2026 | K26: TRANSFER ARM RATTLING NOISE | L26: Kicker Noise | M26: Kicker Module | N26: Apr | O26: 2026 | P26: CA | Q26: 17 | R26: RNext | S26: [ZNF0111AG-CA] Rotimatic Next (Black & Grey) | T26: Processing | U26: 0 | V26: 1 | W26: Return with Refund/Replacement | X26: 50–499
A27: 46231 | B27: Shekar datt maharaj | C27: 81420 | D27: ZM1251250MEG02403 | F27: 128 | G27: Refund with Return | I27: Jul | J27: 2026 | K27: TRANSFER ARM STUCK | L27: Kicker Drive | M27: Kicker Module | N27: Dec | O27: 2025 | P27: ME | Q27: 50 | R27: RNext | S27: [ZNF0111AG-ME] Rotimatic Next (Black & Grey) | T27: Submitted | U27: 65 | V27: 1 | W27: Cancellation | X27: 50–499
A28: 46231 | B28: Rahiman Mohammad | C28: 69178 | D28: ZM1250835CAG02569 | E28: Machine | F28: 1638 | G28: Replacement | H28: RSO09332 | I28: Jul | J28: 2026 | K28: KNEADER BLADE STUCK | L28: Kneader Blade Stuck | M28: Kneader | N28: Aug | O28: 2025 | P28: CA | Q28: 35 | R28: RNext | S28: [ZNF0111AG-CA] Rotimatic Next (Black & Grey) | T28: Processing | U28: 197 | V28: 1 | W28: Return with Refund/Replacement | X28: 1,000–1,999
A29: 46231 | B29: Suchithra Gopinath | C29: 71894 | D29: ZM1251144CAG04882 | E29: Part | F29: 1042 | G29: Replacement | H29: RSO09331 | I29: Jul | J29: 2026 | K29: DAMAGED KICKER | L29: Kicker Catcher Issue | M29: Kicker Module | N29: Nov | O29: 2025 | P29: CA | Q29: 44 | R29: RNext | S29: [2YearRotimaticNextRotimaticCareWarranty] Rotimatic Next - Rotimatic Care Plus Warranty - 2 Years | T29: Closed | U29: 43 | V29: 1 | W29: Return with Refund/Replacement | X29: 1,000–1,999
A30: 46231 | B30: Vijay Subramanyam | C30: 76268 | D30: ZM1251251CAG07726 | F30: 2 | G30: Refund with Return | I30: Jul | J30: 2026 | K30: LEAKAGE | L30: Leakage | M30: Ingredient System | N30: Dec | O30: 2025 | P30: CA | Q30: 51 | R30: RNext | S30: [ZNF0111AG-CA] Rotimatic Next (Black & Grey) | T30: Submitted | U30: 35 | V30: 1 | W30: Cancellation | X30: 0–49
A31: 46231 | B31: ILango Marag | C31: 74743 | D31: ZM1251251CAG07419 | E31: Machine | F31: 756 | G31: Replacement | H31: RSO09330 | I31: Jul | J31: 2026 | K31: TRANSFER ARM RATTLING NOISE | L31: Kicker Noise | M31: Kicker Module | N31: Dec | O31: 2025 | P31: CA | Q31: 51 | R31: RNext | S31: [ZNF0111AG-CA] Rotimatic Next (Black & Grey) | T31: Processing | U31: 0 | V31: 1 | W31: Return with Refund/Replacement | X31: 500–999
A32: 46231 | B32: Chetan Pachchhao | C32: RSO06651 | D32: ZM1260208CAG09764 | E32: Machine | F32: 298 | G32: Replacement | H32: RSO09329 | I32: Jul | J32: 2026 | N32: Feb | O32: 2026 | P32: CA | Q32: 08 | R32: RNext | S32: [ZNF0111AG-CA] Rotimatic Next (Black & Grey) | T32: Processing | U32: 0 | V32: 1 | W32: Return with Refund/Replacement | X32: 50–499
A33: 46231 | B33: Ritika Kureti | C33: RSO02801 | D33: ZM1250415CAG00126 | E33: Machine | F33: 0 | G33: Replacement | H33: RSO09328 | I33: Jul | J33: 2026 | N33: Apr | O33: 2025 | P33: CA | Q33: 15 | R33: RNext | S33: [ZNF0111AG-CA] Rotimatic Next (Black & Grey) | T33: Processing | U33: 0 | V33: 1 | W33: Return with Refund/Replacement | X33: 0–49
A34: 46230 | B34: Sana Chaudhry | C34: 72664 | D34: ZM1251146CAG05219 | E34: Machine | F34: 667 | G34: Replacement | H34: RSO09308 | I34: Jul | J34: 2026 | K34: NOT POWERING ON | L34: Not Powering On | M34: Electrical | N34: Nov | O34: 2025 | P34: CA | Q34: 46 | R34: RNext | S34: [ZNF0111AG-CA] Rotimatic Next (Black & Grey) | T34: Processing | U34: 0 | V34: 1 | W34: Return with Refund/Replacement | X34: 500–999
A35: 46230 | B35: Zebra Khan | C35: 68800 | D35: ZM1251042MEW01583 | E35: Machine | F35: 0 | G35: Replacement | H35: RSO09299 | I35: Jul | J35: 2026 | K35: TRANSFER ARM STUCK | L35: Kicker Drive | M35: Kicker Module | N35: Oct | O35: 2025 | P35: ME | Q35: 42 | R35: RNext | S35: [3YearRotimaticNextRotimaticCareWarranty] Rotimatic Next - Rotimatic Care Plus Warranty - 3 Years | T35: Processing | U35: 153 | V35: 1 | W35: Return with Refund/Replacement | X35: 0–49
A36: 46230 | B36: Nikita Pawar | C36: 78099 | D36: ZM1260311MEG03178 | E36: Machine | F36: 43 | G36: Replacement | H36: RSO09327 | I36: Jul | J36: 2026 | K36: DAMAGED PART INSIDE THE MACHINE | L36: Damaged Component | M36: Assembly/Packaging | N36: Mar | O36: 2026 | P36: ME | Q36: 11 | R36: RNext | S36: [3YearRotimaticNextRotimaticCareWarranty] Rotimatic Next - Rotimatic Care Plus Warranty - 3 Years | T36: Processing | U36: 0 | V36: 1 | W36: Return with Refund/Replacement | X36: 0–49
A37: 46230 | B37: Shambhavi Mohan | C37: 55085 | D37: ZM82405CAB00E | E37: Machine | F37: 2934 | G37: Replacement | H37: RSO09326 | I37: Jul | J37: 2026 | K37: FINAL CHECK STAGE AND DOES NOT PROCEED FURTHER | L37: Final Check Stage Stuck | M37: Others | N37: May | O37: 2024 | P37: B0 | Q37: CA | R37: RPlus | S37: [Extend-Protection-Plan-299.00] Extend Protection Plan - US - 2 Years (299.00) | T37: Processing | U37: 40 | V37: 1 | W37: Return with Refund/Replacement | X37: 2,000–2,999
A38: 46230 | B38: Tarun Kalyani | C38: 67400 | D38: ZM1250940MEG01005 | E38: Part | F38: 523 | G38: Replacement | H38: RSO09325 | I38: Jul | J38: 2026 | K38: DAMAGED KICKER | L38: Kicker Catcher Issue | M38: Kicker Module | N38: Sep | O38: 2025 | P38: ME | Q38: 40 | R38: RNext | S38: [ZNF0111AG-ME] Rotimatic Next (Black & Grey) | T38: Closed | U38: 0 | V38: 1 | W38: Return with Refund/Replacement | X38: 500–999
A39: 46230 | B39: Pavan Reddy | C39: 69167 | D39: ZM125940MEG00998 | E39: Machine | F39: 0 | G39: Replacement | H39: RSO09324 | I39: Jul | J39: 2026 | K39: CANNOT TRANSFER DOUGH BALL | L39: Kicker Drive | M39: Kicker Module | O39: 2025 | P39: EG | Q39: 0M | R39: RNext | S39: [ZNF0111AG-ME] Rotimatic Next (Black & Grey) | T39: Processing | U39: 0 | V39: 1 | W39: Return with Refund/Replacement | X39: 0–49
A40: 46230 | B40: Manoj Deshpande | C40: 72199 | D40: ZM1251146CAW5311 | E40: Machine | F40: 780 | G40: Replacement | H40: RSO09323 | I40: Jul | J40: 2026 | K40: KNEADER TRAY STUCK | L40: Kneader Stuck | M40: Kneader | N40: Nov | O40: 2025 | P40: CA | Q40: 46 | R40: RNext | S40: [2YearRotimaticNextRotimaticCareWarranty] Rotimatic Next - Rotimatic Care Plus Warranty - 2 Years | T40: Processing | U40: 46 | V40: 1 | W40: Return with Refund/Replacement | X40: 500–999
A41: 46230 | B41: Anuj Shah | C41: 71490 | D41: ZM1250940CAWO3534 | E41: Machine | F41: 0 | G41: Replacement | H41: RSO09322 | I41: Jul | J41: 2026 | K41: KNEADER TRAY STUCK | L41: Kneader Stuck | M41: Kneader | N41: Sep | O41: 2025 | P41: CA | Q41: 40 | R41: RNext | S41: [ZNF0111AW-CA] Rotimatic Next (Black & White) | T41: Processing | U41: 227 | V41: 1 | W41: Return with Refund/Replacement | X41: 0–49
A42: 46230 | B42: Aditya Malkar | C42: 72321 | D42: ZM1251249MEW01927 | E42: Machine | F42: 723 | G42: Replacement | H42: RSO09321 | I42: Jul | J42: 2026 | K42: LOADCELL ERROR | L42: Loadcell Error | M42: VT Module | N42: Dec | O42: 2025 | P42: ME | Q42: 49 | R42: RNext | S42: [ZNF0111AW-ME] Rotimatic Next (Black & White) | T42: Processing | U42: 0 | V42: 1 | W42: Return with Refund/Replacement | X42: 500–999
A43: 46230 | B43: Anusha Kanuri | C43: 80312 | D43: ZM1260209CAW09894 | E43: Machine | F43: 125 | G43: Replacement | H43: RSO09320 | I43: Jul | J43: 2026 | K43: NOT POWERING ON | L43: Not Powering On | M43: Electrical | N43: Feb | O43: 2026 | P43: CA | Q43: 09 | R43: RNext | S43: [2YearRotimaticNextRotimaticCareWarranty] Rotimatic Next - Rotimatic Care Plus Warranty - 2 Years | T43: Processing | U43: 34 | V43: 1 | W43: Return with Refund/Replacement | X43: 50–499
A44: 46230 | B44: Ruchika Khanna, Ruchika Khanna | C44: RSO02735 | D44: ZP82503CAB9DD | E44: Machine | F44: 1200 | G44: Replacement | H44: RSO09319 | I44: Jul | J44: 2026 | K44: CRACK | L44: Cracked Machine | M44: Logistics | N44: Mar | O44: 2025 | P44: B9 | Q44: CA | R44: RPlus | S44: [ZMA0111A-CA-R] Remanufactured | T44: Processing | U44: 0 | V44: 1 | W44: Return with Refund/Replacement | X44: 1,000–1,999
A45: 46230 | B45: Krupa Karnik | C45: 69419 | D45: ZM1250937CAG02866 | E45: Machine | F45: 655 | G45: Replacement | H45: RSO09318 | I45: Jul | J45: 2026 | N45: Sep | O45: 2025 | P45: CA | Q45: 37 | R45: RNext | S45: [ZNF0111AG-CA] Rotimatic Next (Black & Grey) | T45: Processing | U45: 42 | V45: 1 | W45: Return with Refund/Replacement | X45: 500–999
A46: 46230 | B46: Shreya Redekar | C46: 64079 | D46: ZM1250623CAG00668 | E46: Machine | F46: 281 | G46: Replacement | H46: RSO09317 | I46: Jul | J46: 2026 | K46: NOT POWERING ON | L46: Not Powering On | M46: Electrical | N46: Jun | O46: 2025 | P46: CA | Q46: 23 | R46: RNext | S46: [ZMA0111A-CA] Rotimatic Plus | T46: Processing | U46: 0 | V46: 1 | W46: Return with Refund/Replacement | X46: 50–499
A47: 46230 | B47: Madhao Wagh | C47: RSO04824 | D47: ZM1251043CAG04144 | E47: Machine | F47: 1487 | G47: Replacement | H47: RSO09316 | I47: Jul | J47: 2026 | K47: NOT POWERING ON | L47: Not Powering On | M47: Electrical | N47: Oct | O47: 2025 | P47: CA | Q47: 43 | R47: RNext | S47: [ZNF0111AG-CA] Rotimatic Next (Black & Grey) | T47: Processing | U47: 0 | V47: 1 | W47: Return with Refund/Replacement | X47: 1,000–1,999
A48: 46230 | B48: BINDIYA MALHOTRA | C48: 70583 | D48: ZM1251043CAG03964 | E48: Machine | F48: 312 | G48: Replacement | H48: RSO09315 | I48: Jul | J48: 2026 | K48: TRANSFER ARM STUCK | L48: Kicker Drive | M48: Kicker Module | N48: Oct | O48: 2025 | P48: CA | Q48: 43 | R48: RNext | S48: [ZNF0111AG-CA] Rotimatic Next (Black & Grey) | T48: Processing | U48: 53 | V48: 1 | W48: Return with Refund/Replacement | X48: 50–499
A49: 46230 | B49: Prasad Kandlakunta | C49: 76873 | D49: ZM1260102CAG08396 | E49: Machine | F49: 0 | G49: Replacement | H49: RSO09314 | I49: Jul | J49: 2026 | N49: Jan | O49: 2026 | P49: CA | Q49: 02 | R49: RNext | S49: [2YearRotimaticNextRotimaticCareWarranty] Rotimatic Next - Rotimatic Care Plus Warranty - 2 Years | T49: Processing | U49: 176 | V49: 1 | W49: Return with Refund/Replacement | X49: 0–49
A50: 46230 | B50: srujeet papakannu | C50: 66313 | D50: ZM1250832CAW02149 | E50: Machine | F50: 1214 | G50: Replacement | H50: RSO09313 | I50: Jul | J50: 2026 | N50: Aug | O50: 2025 | P50: CA | Q50: 32 | R50: RNext | S50: [ZNF0111AW-CA] Rotimatic Next (Black & White) | T50: Processing | U50: 0 | V50: 1 | W50: Return with Refund/Replacement | X50: 1,000–1,999
A51: 46230 | B51: Anjali Bhide | C51: 69602 | D51: ZM1250836CAG02789 | E51: Machine | F51: 875 | G51: Replacement | H51: RSO09312 | I51: Jul | J51: 2026 | K51: TRANSFER ARM STUCK | L51: Kicker Drive | M51: Kicker Module | N51: Aug | O51: 2025 | P51: CA | Q51: 36 | R51: RNext | S51: [ZNF0111AG-CA] Rotimatic Next (Black & Grey) | T51: Processing | U51: 210 | V51: 1 | W51: Return with Refund/Replacement | X51: 500–999
A52: 46230 | B52: Sumit Sethia | C52: 18852 | D52: ZP82205CAA17B | E52: Machine | F52: 7254 | G52: Replacement | H52: RSO09311 | I52: Jul | J52: 2026 | N52: May | O52: 2022 | P52: A1 | Q52: CA | R52: RPlus | S52: [ZMA0111A-CA-R] Remanufactured Replacement | T52: Processing | U52: 0 | V52: 1 | W52: Return with Refund/Replacement | X52: 5,000+
A53: 46230 | B53: Mallika Chandregowda | C53: RSO03808 | D53: ZM1250833MEG00757 | E53: Machine | F53: 610 | G53: Replacement | H53: RSO09310 | I53: Jul | J53: 2026 | K53: STIRRER NOT ROTATING | L53: Stirrer Failure/Stuck | M53: Stirrer | N53: Aug | O53: 2025 | P53: ME | Q53: 33 | R53: RNext | S53: [ZNF0111AG-ME] Rotimatic Next (Black & Grey) | T53: Processing | U53: 0 | V53: 1 | W53: Return with Refund/Replacement | X53: 500–999
A54: 46230 | B54: Batool Fatima | C54: 69488 | D54: ZM1250836CAG02750 | E54: Machine | F54: 1834 | G54: Replacement | H54: RSO09309 | I54: Jul | J54: 2026 | K54: KNEADER BLADE IS STUCK | L54: Kneader Blade Stuck | M54: Kneader | N54: Aug | O54: 2025 | P54: CA | Q54: 36 | R54: RNext | S54: [ZNF0111AG-CA] Rotimatic Next (Black & Grey) | T54: Processing | U54: 50 | V54: 1 | W54: Return with Refund/Replacement | X54: 1,000–1,999
A55: 46230 | B55: pavan nagulapalli | C55: RSO06475 | D55: ZM1260206CAG09404 | E55: Machine | F55: 0 | G55: Replacement | H55: RSO09307 | I55: Jul | J55: 2026 | N55: Feb | O55: 2026 | P55: CA | Q55: 06 | R55: RNext | S55: [ZNF0111AG-CA] Rotimatic Next (Black & Grey) | T55: Processing | U55: 0 | V55: 1 | W55: Return with Refund/Replacement | X55: 0–49
A56: 46230 | B56: Vishal Garg | C56: 77842 | D56: ZM1260208CAG09598 | E56: Machine | F56: 20 | G56: Replacement | H56: RSO09306 | I56: Jul | J56: 2026 | K56: NOT POWERING ON | L56: Not Powering On | M56: Electrical | N56: Feb | O56: 2026 | P56: CA | Q56: 08 | R56: RNext | S56: [ZNF0111AG-CA] Rotimatic Next (Black & Grey) | T56: Processing | U56: 0 | V56: 1 | W56: Return with Refund/Replacement | X56: 0–49
A57: 46230 | B57: Chitra Patel | C57: 67830 | D57: ZM1250938CAG03063 | E57: Machine | F57: 118 | G57: Replacement | H57: RSO09305 | I57: Jul | J57: 2026 | K57: NOT POWERING ON | L57: Not Powering On | M57: Electrical | N57: Sep | O57: 2025 | P57: CA | Q57: 38 | R57: RNext | S57: [ZNF0111AG-CA] Rotimatic Next (Black & Grey) | T57: Processing | U57: 49 | V57: 1 | W57: Return with Refund/Replacement | X57: 50–499
A58: 46230 | B58: Madhulika Singh | C58: 71941 | D58: ZP82510CABA70 | E58: Machine | F58: 0 | G58: Replacement | H58: RSO09303 | I58: Jul | J58: 2026 | K58: HARDWARE ISSUE | L58: General Machine Failure | M58: Other Mechanical | N58: Oct | O58: 2025 | P58: BA | Q58: CA | R58: RPlus | S58: [3YearRemanufacturedRotimaticCareWarranty] Remanufactured - Rotimatic Care Plus Warranty - 3 Years | T58: Processing | U58: 66 | V58: 1 | W58: Return with Refund/Replacement | X58: 0–49
A59: 46230 | B59: Ridhika Shrivastava | C59: 74411 | D59: ZM1251249MEG02158 | E59: Machine | F59: 1774 | G59: Replacement | H59: RSO09302 | I59: Jul | J59: 2026 | K59: VERTICAL TRAY STUCK | L59: VT Stuck | M59: VT Module | N59: Dec | O59: 2025 | P59: ME | Q59: 49 | R59: RNext | S59: [ZNF0111AG-ME] Rotimatic Next (Black & Grey) | T59: Processing | U59: 119 | V59: 1 | W59: Return with Refund/Replacement | X59: 1,000–1,999
A60: 46230 | B60: Tara Tonne | C60: 78686 | D60: ZM1260417CAW10375 | E60: Machine | F60: 20 | G60: Replacement | H60: RSO09301 | I60: Jul | J60: 2026 | K60: NOT POWERING ON | L60: Not Powering On | M60: Electrical | N60: Apr | O60: 2026 | P60: CA | Q60: 17 | R60: RNext | S60: [3YearRotimaticNextRotimaticCareWarranty] Rotimatic Next - Rotimatic Care Plus Warranty - 3 Years | T60: Processing | U60: 39 | V60: 1 | W60: Return with Refund/Replacement | X60: 0–49
A61: 46230 | B61: Dhaval Rana | C61: 71252 | D61: ZM1251041MEG01287 | E61: Machine | F61: 22 | G61: Replacement | H61: RSO09300 | I61: Jul | J61: 2026 | K61: TRANSFER ARM STUCK | L61: Kicker Drive | M61: Kicker Module | N61: Oct | O61: 2025 | P61: ME | Q61: 41 | R61: RNext | S61: [3YearRotimaticNextRotimaticCareWarranty] Rotimatic Next - Rotimatic Care Plus Warranty - 3 Years | T61: Processing | U61: 129 | V61: 1 | W61: Return with Refund/Replacement | X61: 0–49
A62: 46230 | B62: Shreya Srivastava | C62: 79409 | D62: ZM1260417CAG10187 | F62: 166 | G62: Refund with Return | I62: Jul | J62: 2026 | N62: Apr | O62: 2026 | P62: CA | Q62: 17 | R62: RNext | S62: [ZNF0111AG-CA] Rotimatic Next (Black & Grey) | T62: Submitted | U62: 0 | V62: 1 | W62: Cancellation | X62: 50–499
A63: 46230 | B63: sanjeet sahu | C63: RSO07338 | D63: ZM1260102CAG08456 | E63: Machine | F63: 0 | G63: Replacement | H63: RSO09298 | I63: Jul | J63: 2026 | K63: NOT POWERING ON | L63: Not Powering On | M63: Electrical | N63: Jan | O63: 2026 | P63: CA | Q63: 02 | R63: RNext | S63: [ZNF0111AG-CA] Rotimatic Next (Black & Grey) | T63: Processing | U63: 0 | V63: 1 | W63: Return with Refund/Replacement | X63: 0–49
A64: 46230 | B64: Dipti Amlani | C64: 67687 | D64: ZM1250727MEW00221 | E64: Machine | F64: 907 | G64: Replacement | H64: RSO09297 | I64: Jul | J64: 2026 | K64: RATTLING NOISE | L64: Rattling Noise | M64: Kicker Module | N64: Jul | O64: 2025 | P64: ME | Q64: 27 | R64: RNext | S64: [ZNF0111AW-ME] Rotimatic Next (Black & White) | T64: Processing | U64: 150 | V64: 1 | W64: Return with Refund/Replacement | X64: 500–999
A65: 46230 | B65: HARSHA B REDDY | C65: 71348 | D65: ZM1251144CAG04802 | E65: Machine | F65: 272 | G65: Replacement | H65: RSO09296 | I65: Jul | J65: 2026 | K65: TRANSFER ARM STUCK | L65: Kicker Drive | M65: Kicker Module | N65: Nov | O65: 2025 | P65: CA | Q65: 44 | R65: RNext | S65: [ZNF0111AG-CA] Rotimatic Next (Black & Grey) | T65: Processing | U65: 44 | V65: 1 | W65: Return with Refund/Replacement | X65: 50–499
A66: 46230 | B66: SIDDHARTHA SINGH | C66: 64533 | D66: ZM1250625CAG01107 | E66: Machine | F66: 0 | G66: Replacement | H66: RSO09295 | I66: Jul | J66: 2026 | K66: NOT POWERING ON | L66: Not Powering On | M66: Electrical | N66: Jun | O66: 2025 | P66: CA | Q66: 25 | R66: RNext | S66: [ZNF0111AG-CA] Rotimatic Next (Black & Grey) | T66: Processing | U66: 0 | V66: 1 | W66: Return with Refund/Replacement | X66: 0–49
A67: 46230 | B67: Lakhshya Bansal | C67: RSO07389 | D67: ZM1260102CAG08337 | E67: Machine | F67: 279 | G67: Replacement | H67: RSO09294 | I67: Jul | J67: 2026 | K67: TRANSFER ARM STUCK | L67: Kicker Drive | M67: Kicker Module | N67: Jan | O67: 2026 | P67: CA | Q67: 02 | R67: RNext | S67: [ZNF0111AG-CA] Rotimatic Next (Black & Grey) | T67: Processing | U67: 0 | V67: 1 | W67: Return with Refund/Replacement | X67: 50–499
A68: 46230 | B68: Nikita Rasam | C68: 64429 | D68: ZM12512CAG06370 | E68: Machine | F68: 0 | G68: Replacement | H68: RSO09293 | I68: Jul | J68: 2026 | N68: Dec | O68: 2025 | P68: G0 | Q68: CA | R68: RNext | S68: [ZNF0111AW-CA] Rotimatic Next (Black & White) | T68: Processing | U68: 0 | V68: 1 | W68: Return with Refund/Replacement | X68: 0–49
A69: 46230 | B69: Shabbir Bharmal | C69: 77793 | D69: ZM1260208CAG09684 | E69: Machine | F69: 135 | G69: Replacement | H69: RSO09291 | I69: Jul | J69: 2026 | K69: NOT POWERING ON | L69: Not Powering On | M69: Electrical | N69: Feb | O69: 2026 | P69: CA | Q69: 08 | R69: RNext | S69: [3YearRotimaticNextRotimaticCareWarranty] Rotimatic Next - Rotimatic Care Plus Warranty - 3 Years | T69: Processing | U69: 52 | V69: 1 | W69: Return with Refund/Replacement | X69: 50–499
A70: 46230 | B70: Beni Verma | C70: 78084 | D70: ZM1260104CAW08928 | E70: Machine | F70: 20 | G70: Replacement | H70: RSO09289 | I70: Jul | J70: 2026 | K70: NOT POWERING ON | L70: Not Powering On | M70: Electrical | N70: Jan | O70: 2026 | P70: CA | Q70: 04 | R70: RNext | S70: [ZNF0111AW-CA] Rotimatic Next (Black & White) | T70: Processing | U70: 36 | V70: 1 | W70: Return with Refund/Replacement | X70: 0–49
A71: 46230 | B71: Neeraj Vig | C71: 70740 | D71: ZM1251144CAG04302 | E71: Machine | F71: 2250 | G71: Replacement | H71: RSO09288 | I71: Jul | J71: 2026 | K71: TRANSFER ARM RATTLING NOISE | L71: Kicker Noise | M71: Kicker Module | N71: Nov | O71: 2025 | P71: CA | Q71: 44 | R71: RNext | S71: [ZNF0111AG-CA] Rotimatic Next (Black & Grey) | T71: Processing | U71: 53 | V71: 1 | W71: Return with Refund/Replacement | X71: 2,000–2,999
A72: 46230 | B72: Sunil Biswal | C72: 65050 | D72: ZM1250627MEG00198 | E72: Machine | F72: 788 | G72: Replacement | H72: RSO09287 | I72: Jul | J72: 2026 | K72: STIRRER NOT ROTATING | L72: Stirrer Failure/Stuck | M72: Stirrer | N72: Jun | O72: 2025 | P72: ME | Q72: 27 | R72: RNext | S72: [ZNF0111AG-ME] Rotimatic Next (Black & Grey) | T72: Processing | U72: 85 | V72: 1 | W72: Return with Refund/Replacement | X72: 500–999
A73: 46230 | B73: Shweta Patel | C73: 78328 | D73: ZM1260209MEG02957 | E73: Machine | F73: 1291 | G73: Replacement | H73: RSO09286 | I73: Jul | J73: 2026 | K73: CANNOT TRANSFER DOUGH BALL | L73: Kicker Drive | M73: Kicker Module | N73: Feb | O73: 2026 | P73: ME | Q73: 09 | R73: RNext | S73: [2YearRotimaticNextRotimaticCareWarranty] Rotimatic Next - Rotimatic Care Plus Warranty - 2 Years | T73: Processing | U73: 0 | V73: 1 | W73: Return with Refund/Replacement | X73: 1,000–1,999
A74: 46230 | B74: Unmesh Vhatkar | C74: RSO05798 | D74: ZM1251249CAG06299 | E74: Machine | F74: 2035 | G74: Replacement | H74: RSO09285 | I74: Jul | J74: 2026 | K74: CANNOT TRANSFER DOUGH BALL | L74: Kicker Drive | M74: Kicker Module | N74: Dec | O74: 2025 | P74: CA | Q74: 49 | R74: RNext | S74: [ZNF0111AG-CA] Rotimatic Next (Black & Grey) | T74: Processing | U74: 0 | V74: 1 | W74: Return with Refund/Replacement | X74: 2,000–2,999
A75: 46230 | B75: Satinder Atwal | C75: 79694 | D75: ZM1260208CAG09743 | E75: Machine | F75: 656 | G75: Replacement | H75: RSO09284 | I75: Jul | J75: 2026 | K75: TRANSFER ARM STUCK | L75: Kicker Drive | M75: Kicker Module | N75: Feb | O75: 2026 | P75: CA | Q75: 08 | R75: RNext | S75: [ZNF0111AG-CA] Rotimatic Next (Black & Grey) | T75: Processing | U75: 108 | V75: 1 | W75: Return with Refund/Replacement | X75: 500–999
A76: 46230 | B76: Albin Varghese | C76: RSO07652 | D76: ZM1260311MEG03165 | E76: Machine | F76: 21 | G76: Replacement | H76: RSO09283 | I76: Jul | J76: 2026 | K76: CANNOT TRANSFER DOUGH BALL | L76: Kicker Drive | M76: Kicker Module | N76: Mar | O76: 2026 | P76: ME | Q76: 11 | R76: RNext | S76: [ZNF0111AG-ME] Rotimatic Next (Black & Grey) | T76: Processing | U76: 0 | V76: 1 | W76: Return with Refund/Replacement | X76: 0–49
A77: 46229 | B77: Dimple Sethi | C77: 76219 | D77: ZM1251251CAG07004 | E77: Machine | F77: 642 | G77: Replacement | H77: RSO09282 | I77: Jul | J77: 2026 | K77: NOT POWERING ON | L77: Not Powering On | M77: Electrical | N77: Dec | O77: 2025 | P77: CA | Q77: 51 | R77: RNext | S77: [3YearRotimaticNextRotimaticCareWarranty] Rotimatic Next - Rotimatic Care Plus Warranty - 3 Years | T77: Processing | U77: 36 | V77: 1 | W77: Return with Refund/Replacement | X77: 500–999
A78: 46229 | B78: Eisha Hussaini | C78: RSO05118 | D78: ZM1251043CAG03945 | E78: Machine | F78: 988 | G78: Replacement | H78: RSO09281 | I78: Jul | J78: 2026 | K78: NOT POWERING ON | L78: Not Powering On | M78: Electrical | N78: Oct | O78: 2025 | P78: CA | Q78: 43 | R78: RNext | S78: [ZNF0111AG-CA] Rotimatic Next (Black & Grey) | T78: Processing | U78: 0 | V78: 1 | W78: Return with Refund/Replacement | X78: 500–999
A79: 46229 | B79: Kedar Afaley | C79: 74703 | D79: ZM1251251CAG06801 | E79: Machine | F79: 3069 | G79: Replacement | H79: RSO09280 | I79: Jul | J79: 2026 | K79: TRANSFER ARM STUCK | L79: Kicker Drive | M79: Kicker Module | N79: Dec | O79: 2025 | P79: CA | Q79: 51 | R79: RNext | S79: [ZNF0111AG-CA] Rotimatic Next (Black & Grey) | T79: Processing | U79: 116 | V79: 1 | W79: Return with Refund/Replacement | X79: 3,000–3,999
A80: 46229 | B80: Mohnish Bhagde | C80: RSO04684 | D80: ZM1251144CAW04433 | E80: Machine | F80: 721 | G80: Replacement | H80: RSO09279 | I80: Jul | J80: 2026 | K80: NOT POWERING ON | L80: Not Powering On | M80: Electrical | N80: Nov | O80: 2025 | P80: CA | Q80: 44 | R80: RNext | S80: [ZNF0111AW-CA] Rotimatic Next (Black & White) | T80: Closed | U80: 0 | V80: 1 | W80: Return with Refund/Replacement | X80: 500–999
... A87: 46227 | B87: punit solanki | C87: RSO06956 | D87: ZM1260104CAW08818 | E87: Machine | F87: 50 | G87: Replacement | H87: RSO09026 | I87: Jul | J87: 2026 | K87: NOT POWERING ON | L87: Not Powering On | M87: Electrical | N87: Jan | O87: 2026 | P87: CA | Q87: 04 | R87: RNext | S87: [ZNF0111AW-CA] Rotimatic Next (Black & White) | T87: Processing | U87: 0 | V87: 1 | W87: Return with Refund/Replacement | X87: 50–499
A88: 46227 | B88: Jasleen Kaur | C88: 69905 | D88: ZM1260104CAW08810 | F88: 0 | G88: Refund with Return | I88: Jul | J88: 2026 | K88: PAN STUCK | L88: Press Pan Malfunction | M88: Press Pan Module | N88: Jan | O88: 2026 | P88: CA | Q88: 04 | R88: RNext | S88: [1YearRotimaticNextRotimaticCareWarranty] Rotimatic Next - Rotimatic Care Plus Warranty - 1 Year | T88: Submitted | U88: 46 | V88: 1 | W88: Cancellation | X88: 0–49
A89: 46227 | B89: Sohan Nipunage | C89: 83079 | D89: ZM1260417CAW10481 | E89: Machine | F89: 307 | G89: Replacement | I89: Jul | J89: 2026 | K89: TRANSFER ARM STUCK | L89: Kicker Drive | M89: Kicker Module | N89: Apr | O89: 2026 | P89: CA | Q89: 17 | R89: RNext | S89: [2YearRotimaticNextRotimaticCareWarranty] Rotimatic Next - Rotimatic Care Plus Warranty - 2 Years | T89: Submitted | U89: 0 | V89: 1 | W89: Return with Refund/Replacement | X89: 50–499
A90: 46227 | B90: Ahmed Khattak | C90: 66952 | D90: ZM1250728MEG00411 | E90: Machine | F90: 0 | G90: Replacement | H90: RSO09049 | I90: Jul | J90: 2026 | K90: DISPENSING POSITION NOT CORRECT | L90: Incorrect Dispensing Position | M90: Ingredient System | N90: Jul | O90: 2025 | P90: ME | Q90: 28 | R90: RNext | S90: [ZNF0111AG-ME] Rotimatic Next (Black & Grey) | T90: Processing | U90: 168 | V90: 1 | W90: Return with Refund/Replacement | X90: 0–49
A91: 46227 | B91: Akarsh Singh | C91: 64583 | D91: ZM1250730MEG00566 | E91: Machine | F91: 526 | G91: Replacement | H91: RSO08974 | I91: Jul | J91: 2026 | K91: STIRRER NOT ROTATING | L91: Stirrer Failure/Stuck | M91: Stirrer | N91: Jul | O91: 2025 | P91: ME | Q91: 30 | R91: RNext | S91: [ZMA0111A-ME] Rotimatic Plus | T91: Processing | U91: 94 | V91: 1 | W91: Return with Refund/Replacement | X91: 500–999
A92: 46227 | B92: Aditya Bhambhu | C92: RSO07820 | D92: ZM1260417CAW10417 | E92: Machine | F92: 2104 | G92: Replacement | H92: RSO09050 | I92: Jul | J92: 2026 | K92: CANNOT TRANSFER DOUGH BALL | L92: Kicker Drive | M92: Kicker Module | N92: Apr | O92: 2026 | P92: CA | Q92: 17 | R92: RNext | S92: [ZNF0111AW-CA] Rotimatic Next (Black & White) | T92: Processing | U92: 0 | V92: 1 | W92: Return with Refund/Replacement | X92: 2,000–2,999
A93: 46227 | B93: Vaama Patel | C93: 77736 | D93: ZM1260102CAG08499 | E93: Machine | F93: 183 | G93: Replacement | I93: Jul | J93: 2026 | K93: KNEADER TRAY STUCK | L93: Kneader Stuck | M93: Kneader | N93: Jan | O93: 2026 | P93: CA | Q93: 02 | R93: RNext | S93: [ZNF0111AG-CA] Rotimatic Next (Black & Grey) | T93: Submitted | U93: 37 | V93: 1 | W93: Return with Refund/Replacement | X93: 50–499
A94: 46227 | B94: Vineet Mehra | C94: 68091 | D94: ZM1250731CAG01910 | E94: Machine | F94: 76 | G94: Replacement | I94: Jul | J94: 2026 | K94: KNEADER BLADE STUCK | L94: Kneader Blade Stuck | M94: Kneader | N94: Jul | O94: 2025 | P94: CA | Q94: 31 | R94: RNext | S94: [ZNF0111AG-CA] Rotimatic Next (Black & Grey) | T94: Submitted | U94: 59 | V94: 1 | W94: Return with Refund/Replacement | X94: 50–499
A95: 46227 | B95: Vibha Vig | C95: RSO05068 | D95: ZM1251144CAW04359 | E95: Machine | F95: 479 | G95: Replacement | I95: Jul | J95: 2026 | K95: NOT POWERING ON | L95: Not Powering On | M95: Electrical | N95: Nov | O95: 2025 | P95: CA | Q95: 44 | R95: RNext | S95: [ZNF0111AW-CA] Rotimatic Next (Black & White) | T95: Submitted | U95: 0 | V95: 1 | W95: Return with Refund/Replacement | X95: 50–499
A96: 46227 | B96: Anjushma Sharma | C96: 78169 | D96: ZM1260209MEG03025 | E96: Machine | F96: 570 | G96: Replacement | I96: Jul | J96: 2026 | K96: TRANSFER ARM RATTLING NOISE | L96: Kicker Noise | M96: Kicker Module | N96: Feb | O96: 2026 | P96: ME | Q96: 09 | R96: RNext | S96: [3YearRotimaticNextRotimaticCareWarranty] Rotimatic Next - Rotimatic Care Plus Warranty - 3 Years | T96: Submitted | U96: 0 | V96: 1 | W96: Return with Refund/Replacement | X96: 500–999
A97: 46227 | B97: Sarika Dawar | C97: RSO06183 | D97: ZM1251251CAG06824 | E97: Machine | F97: 1835 | G97: Replacement | I97: Jul | J97: 2026 | K97: SLAVE COMMUNICATION ERROR | L97: Slave Communication Error | M97: Electrical | N97: Dec | O97: 2025 | P97: CA | Q97: 51 | R97: RNext | S97: [ZNF0111AG-CA] Rotimatic Next (Black & Grey) | T97: Submitted | U97: 0 | V97: 1 | W97: Return with Refund/Replacement | X97: 1,000–1,999
A98: 46227 | B98: Shailendra Kontham | C98: RSO05431 | D98: ZM1251146CAG05336 | E98: Machine | F98: 670 | G98: Replacement | I98: Jul | J98: 2026 | K98: DB DETECTION WARNING | L98: DB Detection Warning | M98: VT Module | N98: Nov | O98: 2025 | P98: CA | Q98: 46 | R98: RNext | S98: [ZNF0111AG-CA] Rotimatic Next (Black & Grey) | T98: Submitted | U98: 0 | V98: 1 | W98: Return with Refund/Replacement | X98: 500–999
A99: 46227 | B99: Vishal Saraf | C99: 76393 | D99: ZM1260206MEG02551 | E99: Machine | F99: 639 | G99: Replacement | I99: Jul | J99: 2026 | K99: TRANSFER ARM STUCK | L99: Kicker Drive | M99: Kicker Module | N99: Feb | O99: 2026 | P99: ME | Q99: 06 | R99: RNext | S99: [ZNF0111AG-ME] Rotimatic Next (Black & Grey) | T99: Submitted | U99: 78 | V99: 1 | W99: Return with Refund/Replacement | X99: 500–999
A100: 46227 | B100: Amol Parkhe | C100: 68728 | D100: ZM1250833MEG00748 | E100: Machine | F100: 1796 | G100: Replacement | I100: Jul | J100: 2026 | K100: PRESS PAN STUCK | L100: Press Pan Malfunction | M100: Press Pan Module | N100: Aug | O100: 2025 | P100: ME | Q100: 33 | R100: RNext | S100: [ZNF0111AG-ME] Rotimatic Next (Black & Grey) | T100: Submitted | U100: 0 | V100: 1 | W100: Return with Refund/Replacement | X100: 1,000–1,999
A101: 46227 | B101: Nobal Niraula | C101: 77396 | D101: ZM1260102CAG08289 | E101: Machine | F101: 123 | G101: Replacement | I101: Jul | J101: 2026 | K101: COLOUR MISMATCH | L101: Color Mismatch | M101: Logistics | N101: Jan | O101: 2026 | P101: CA | Q101: 02 | R101: RNext | S101: [ZNF0111AW-CA] Rotimatic Next (Black & White) | T101: Submitted | U101: 37 | V101: 1 | W101: Return with Refund/Replacement | X101: 50–499
A102: 46227 | B102: Umesh Nitnaware | C102: RSO07881 | D102: ZM1260104CAW09015 | E102: Machine | F102: 192 | G102: Replacement | I102: Jul | J102: 2026 | K102: LOOSE VERTICAL TRAY | L102: VT Loose | M102: Assembly/Packaging | N102: Jan | O102: 2026 | P102: CA | Q102: 04 | R102: RNext | S102: [ZNF0111AG-CA] Rotimatic Next (Black & Grey) | T102: Submitted | U102: 0 | V102: 1 | W102: Return with Refund/Replacement | X102: 50–499
A103: 46227 | B103: Shivank Goel | C103: 67211 | D103: ZM1250521CAG00414 | E103: Machine | F103: 1012 | G103: Replacement | I103: Jul | J103: 2026 | K103: CRACKED SIDE COVER | L103: Cracked Machine | M103: Logistics | N103: May | O103: 2025 | P103: CA | Q103: 21 | R103: RNext | S103: [ZNF0111AG-CA] Rotimatic Next (Black & Grey) | T103: Submitted | U103: 0 | V103: 1 | W103: Return with Refund/Replacement | X103: 1,000–1,999
A104: 46227 | B104: Nitin Waghmode | C104: 62918 | D104: ZM1250626CAW01186 | E104: Machine | F104: 1857 | G104: Replacement | I104: Jul | J104: 2026 | K104: KNEADER BLADE STUCK | L104: Kneader Blade Stuck | M104: Kneader | N104: Jun | O104: 2025 | P104: CA | Q104: 26 | R104: RNext | S104: [Extend-Protection-Plan-299.00] Extend Protection Plan - US - 2 Years (299.00) | T104: Submitted | U104: 0 | V104: 1 | W104: Return with Refund/Replacement | X104: 1,000–1,999
... A117: 46226 | B117: Hemanth Buchireddy | C117: 71911 | D117: ZM1251144CAG04582 | E117: Machine | F117: 1340 | G117: Replacement | I117: Jul | J117: 2026 | K117: PRESS PAN STUCK | L117: Press Pan Malfunction | M117: Press Pan Module | N117: Nov | O117: 2025 | P117: CA | Q117: 44 | R117: RNext | S117: [ZNF0111AG-CA] Rotimatic Next (Black & Grey) | T117: Submitted | U117: 42 | V117: 1 | W117: Return with Refund/Replacement | X117: 1,000–1,999
A118: 46226 | B118: RAHUL NAIK | C118: 65257 | D118: ZM1250727MEW00228 | E118: Machine | F118: 2081 | G118: Replacement | H118: RSO08972 | I118: Jul | J118: 2026 | K118: STIRRER NOT ROTATING | L118: Stirrer Failure/Stuck | M118: Stirrer | N118: Jul | O118: 2025 | P118: ME | Q118: 27 | R118: RNext | S118: [ZNF0111AW-ME] Rotimatic Next (Black & White) | T118: Processing | U118: 145 | V118: 1 | W118: Return with Refund/Replacement | X118: 2,000–2,999
...

Sheet Field RMA
A1: Issue Reported Date | B1: Customer's Name | C1: Order# | D1: MachineSerialNumber | E1: Return Type | F1: Roti Count | G1: Notes_Clean
A2: 46225 | B2: Robin Chandil | C2: 78583 | D2: ZM1260417CAW10378 | E2: Replacement | F2: 352 | G2: VT STUCK
A3: 46225 | B3: Achal Dave | C3: 79532 | D3: ZM1260209MEG02947 | E3: Replacement | F3: 163 | G3: KNEADER TRAY STUCK
A4: 46225 | B4: Akhil Reddy Sabhapathi | C4: 65327 | D4: ZM1250729CAG01659 | E4: Replacement | F4: 13 | G4: TRANSFER ARM RATTLING NOISE
A5: 46225 | B5: Sarthak Arora | C5: 73058 | D5: ZM1251147CAG05568 | E5: Replacement | F5: 29 | G5: FLOUR SPILLAGE
A6: 46225 | B6: Prathamesh Thakur | C6: 66415 | D6: ZM1250835MEG00900 | E6: Replacement | F6: 394 | G6: TRANSFER ARM STUCK
A7: 46225 | B7: LEKHRAJ PATEL | C7: 82057 | D7: ZM1260311CAW09973 | E7: Replacement | F7: 182 | G7: TRANSFER ARM RATTLING NOISE
A8: 46225 | B8: Ashwini Metkar | C8: RSO02723 | D8: ZM1250835CAG02550 | E8: Replacement | F8: 314 | G8: TOP CASING CRACK
A9: 46225 | B9: Rushikesh Veni | C9: RSO03479 | D9: ZM1250728CAG01460 | E9: Replacement | F9: 1613 | G9: KNEADER TRAY STUCK
A10: 46225 | B10: Vikrant Yagnick | C10: RSO04349 | D10: ZM1250939CAW03194 | E10: Replacement | F10: 1000 | G10: BROKEN KICKER RAIL
A11: 46225 | B11: Rhythm Varshney | C11: 66755 | D11: ZM1250729CAG01651 | E11: Replacement | F11: 1466 | G11: TRANSFER ARM RATTLING NOISE
A12: 46225 | B12: Rahul Arke | C12: 64335 | D12: ZM1250625CAG00938 | E12: Replacement | F12: 1803 | G12: KNEADER TRAY STUCK
A13: 46225 | B13: Rajeev Kumar | C13: 72057 | D13: ZM1251147CAG05608 | E13: Replacement | F13: 1725 | G13: CANNOT TRANSFER DOUGHBALL
A14: 46224 | B14: Shambhavi Mohan | C14: 55085 | D14: ZM82405CAB00E | E14: Replacement | F14: 2934 | G14: MACHINE FAILURE
A15: 46223 | B15: Jayaprakash Rajendran | C15: 49968 | D15: ZM1260206MEG02650 | F15: 196 | G15: UNABLE TO USE MILLER UPDATE
A16: 46220 | B16: Vishnu Sreekumar | C16: 63119 | D16: ZM1250626CAW01331 | F16: 386 | G16: NOT POWERING ON
A17: 46220 | B17: Dipesh Malik | C17: 69886 | D17: ZM1251249MEG02117 | E17: Replacement | F17: 20 | G17: STIRRER NOT ROTATING
A18: 46219 | B18: Dines Kumar Kesa | C18: 68894 | D18: ZM1250937CAG02883 | E18: Replacement | F18: 311 | G18: KNEAD BLADE STUCK
A19: 46219 | B19: Bhajneek Bajwa | C19: RSO05458 | D19: ZM1251147CAG05389 | E19: Replacement | F19: 1305 | G19: APPROVED BY PARUL
A20: 46219 | B20: VIVEK CHITTAMURI | C20: 76575 | D20: ZM1251251CAG07874 | E20: Replacement | F20: 1028 | G20: TRANSFER ARM RATTLING NOISE
A21: 46219 | B21: Amit kumar | C21: 71946 | D21: ZM1251041MEG01314 | F21: 831 | G21: DAMAGED KICKER
A22: 46219 | B22: Prakash Gudsoorkar | C22: 63988 | D22: ZM1250834CAG02539 | F22: 988 | G22: PANS NOT HEATING
A23: 46219 | B23: Mansoor Wani | C23: 67495 | D23: ZM1251249MEG01965 | F23: 0 | G23: LOAD CELL ISSUE
A24: 46218 | B24: Sharad Kumar Sangal | C24: 79171 | D24: ZM1260417CAG10142 | E24: Parts Replacement | F24: 362 | G24: DAMAGED KICKER
A25: 46218 | B25: Shubhanshu Verma | C25: 72393 | D25: ZM1251251CAG07860 | E25: Parts Replacement | F25: 154 | G25: DAMAGED STIRRER
A26: 46218 | B26: Jaydeep Taralkar | C26: 71712 | D26: ZM1251249CAW06239 | E26: Parts Replacement | F26: 26 | G26: DAMAGED KICKER
A27: 46218 | B27: Ritvika Sharma | C27: 75442 | D27: ZM1251251CAG07209 | E27: Parts Replacement | F27: 917 | G27: DAMAGED KICKER
A28: 46218 | B28: Desh Deepak | C28: 75509 | D28: ZM1251147CAW05762 | G28: NA
A29: 46217 | B29: Simar Jaggi | C29: 67652 | D29: ZM1250937CAG02886 | E29: Parts Replacement | F29: 583 | G29: DAMAGED KICKER
A30: 46217 | B30: Deepika Udhani | C30: 48844 | D30: ZM82402MEB023 | E30: Replacement | G30: OIL LEAKAGE
A31: 46217 | B31: Shobana Subramani | C31: 74158 | D31: ZM1260102CAG08281 | E31: Parts Replacement | F31: 32 | G31: DAMAGED KICKER
A32: 46217 | B32: Darakshan Anwar | C32: 74473 | D32: ZM1260104CAW09076 | E32: Parts Replacement | F32: 0 | G32: DAMAGED KICKER
A33: 46217 | B33: Harita Dave | C33: 73105 | D33: ZM1251251CAG07899 | E33: Parts Replacement | F33: 849 | G33: DAMAGED KICKER
A34: 46217 | B34: Nirav Ginwala | C34: 63441 | D34: ZM1250836CAG02739 | E34: Parts Replacement | F34: 1235 | G34: DAMAGED KICKER
A35: 46217 | B35: Damini Desai | C35: 68632 | D35: ZM1251147CAG05421 | G35: CANNOT TRANSFER DOUGHBALL
A36: 46216 | B36: Shirish Chandrashekhar Jambhorkar | C36: 72298 | D36: ZM1251042MEW01573 | G36: KICKER RAIL UNPARALLEL
A37: 46216 | B37: Hardik Shah | C37: 63651 | D37: ZM1250626CAW01336 | E37: Replacement | F37: 593 | G37: LOUD KNEADING NOISE
A38: 46216 | B38: Hemant Phadnis | C38: 75945 | D38: ZM1260104CAW08975 | E38: Replacement | G38: CANNOT DISPENSE WATER
A39: 46216 | B39: somdeb chatterjee | C39: 64684 | D39: ZM1250730CAW01944 | E39: Parts Replacement | F39: 753 | G39: DAMAGED KICKER
A40: 46216 | B40: Bhavesh Bhandarker | C40: 78568 | D40: ZM1260311MEG03266 | E40: Replacement | F40: 0 | G40: CANNOT CONNECT TO WI-FI
A41: 46216 | B41: syed irtaza Hussain | C41: RSO04848 | D41: ZM1251042MEG01482 | E41: Replacement | F41: 3963 | G41: TRANSFER ARM STUCK
A42: 46216 | B42: Mohit Saxena | C42: 79665 | D42: ZM1260417CAG10069 | E42: Parts Replacement | F42: 222 | G42: DAMAGED KICKER
A43: 46216 | B43: AJAY MANCHANDA | C43: 76300 | D43: ZM1260209MEW02831 | E43: Replacement | F43: 0 | G43: TRANSFER ARM RATTLING NOISE
A44: 46216 | B44: Shahnoor Sarvari | C44: 63179 | D44: ZM1250417CAG00247 | E44: Replacement | F44: 0 | G44: DISPENSING POSITION NOT CORRECT
A45: 46216 | B45: pawan wattamwar | C45: RSO04842 | D45: ZM1251043CAG04155 | E45: Replacement | F45: 2177 | G45: NOT POWERING ON
A46: 46216 | B46: AMIT L PANDE | C46: RSO06560 | D46: ZM1260208CAW09514 | E46: Replacement | F46: 420 | G46: TRANSFER ARM STUCK
A47: 46216 | B47: Pooja Belani | C47: 64319 | D47: ZM1250728CAG01515 | E47: Replacement | F47: 1285 | G47: KNEADER TRAY STUCK
A48: 46216 | B48: Sibin GLADSTON SUSHAMA | C48: 65478 | D48: ZM1250729CAG01668 | E48: Replacement | F48: 1360 | G48: TRANSFER ARM RATTLING NOISE
A49: 46216 | B49: Muhammed Waseem Butt | C49: 71638 | D49: ZM1250835MEW00865 | E49: Replacement | F49: 145 | G49: KNEAD BLADE STUCK
A50: 46216 | B50: Rupinder Singh | C50: 76181 | D50: ZM1251249MEG02124 | E50: Replacement | F50: 716 | G50: PRESS PAN STUCK
... A154: 46213 | B154: Gaurav Gangwal | C154: 81027 | D154: ZM1260311CAW09980 | E154: Replacement | F154: 287 | G154: TRANSFER ARM STUCK
A155: 46212 | B155: CHIDANANDA BAID | C155: 65175 | D155: ZM1250938CAG03060 | G155: PANS NOT HEATING
A156: 46212 | B156: Akhilendra Verma | C156: 76023 | D156: ZM1260209MEG03036 | G156: GHOST TOUCH
A157: 46212 | B157: Achal Dave | C157: 79532 | D157: ZM1260209MEG02947 | E157: Parts Replacement | F157: 619 | G157: DAMAGED STIRRER
A158: 46212 | B158: Sreenivasulu Borra | C158: 63636 | D158: ZM1250626CAW01435 | E158: Replacement | F158: 901 | G158: BROKEN VT
A159: 46211 | B159: Chandni Sutariya | C159: 80888 | D159: ZM1260209MEW02749 | E159: Parts Replacement | F159: 488 | G159: DAMAGED KICKER
A160: 46211 | B160: Sheeba Farhat | C160: 74729 | D160: ZM1251251CAG07260 | E160: Parts Replacement | F160: 1228 | G160: DAMAGED KICKER
A161: 46211 | B161: Kumar Rai | C161: RSO05338 | D161: ZM1251144CAG04880 | E161: Replacement | F161: 490 | G161: TRANSFER ARM RATTLING NOISE
A162: 46211 | B162: Parin Shah | C162: 65138 | D162: ZM1250627MEG00171 | E162: Parts Replacement | F162: 865 | G162: DAMAGED KICKER
A163: 46211 | B163: Jaydeep Taralkar | C163: 71712 | D163: ZM1251249CAW06239 | E163: Parts Replacement | F163: 1709 | G163: DAMAGED KICKER
A164: 46211 | B164: Aparna Warade | C164: 71935 | D164: ZM1260104CAW09050 | E164: Parts Replacement | F164: 300 | G164: DAMAGED KICKER
A165: 46210 | B165: AKSHAY GHORPADE | C165: 74534 | D165: ZM1251251CAG07146 | E165: Parts Replacement | F165: 909 | G165: DAMAGED KICKER
A166: 46210 | B166: Chirag Jain | C166: 76294 | D166: ZM1251251CAG07967 | E166: Parts Replacement | F166: 370 | G166: DAMAGED KICKER
A167: 46210 | B167: JALAJ KUMAR | C167: 65964 | D167: ZM1250728CAG01462 | E167: Replacement | F167: 78 | G167: FLOUR CONTAINER/MOTOR DAMAGED
A168: 46210 | B168: Mansi Narlawar | C168: 74201 | D168: ZM1260102CAG08062 | E168: Parts Replacement | F168: 538 | G168: DAMAGED KICKER
... A174: 46209 | B174: Himanshu Kamat | C174: 75874 | D174: ZM1260206MEG02534 | E174: Replacement | F174: 575 | G174: PARTIALLY UNCOOKED
A175: 46209 | B175: Jyoti Madhwani | C175: 69802 | D175: ZM1250730MEG00620 | E175: Parts Replacement | F175: 826
A176: 46209 | B176: Aparna Manney | C176: IN2713 | D176: ZM1260206MEG02723 | E176: Replacement
A177: 46209 | B177: Lomesha Thakore | C177: 78126 | D177: ZM1260206MEG02622 | E177: Parts Replacement | F177: 229
A178: 46209 | B178: Kuldeep singh | C178: IN2406 | D178: ZM1250940MEG01162 | E178: Parts Replacement | F178: 673 | G178: DAMAGED FLOUR AND WATER CONTAINER
A179: 46209 | B179: Inderpreet Sandhu | C179: 74282 | D179: ZM1251251CAG06989 | G179: TRANSFER ARM RATTLING NOISE
A180: 46209 | B180: Munawer Shafi | C180: 75478 | D180: ZM1260105MEW02442 | E180: Parts Replacement | F180: 842 | G180: DAMAGED KICKER
A181: 46209 | B181: Sasha Sutaria | C181: 76869 | D181: ZM1260206MEG02530 | E181: Parts Replacement | F181: 0 | G181: DAMAGED FRONT DOOR
A182: 46209 | B182: Meeta Jayaswal | C182: 63995 | D182: ZM1251043CAG04156 | E182: Parts Replacement | F182: 1164 | G182: DAMAGED STIRRER
A183: 46209 | B183: Mittal Patel | C183: 66212 | D183: ZM1250835CAG02638 | E183: Parts Replacement | F183: 684 | G183: DAMAGED KICKER
A184: 46209 | B184: Karthik Somesula | C184: 71896 | D184: ZM1251147CAW05801 | E184: Parts Replacement | F184: 590 | G184: DAMAGED KICKER
A185: 46208 | B185: Megha Modi | C185: 76061 | D185: ZM126010A4CAW08970 | F185: 0
A186: 46206 | B186: Vishalkumar Dave | C186: 68955 | D186: ZM1250937CAG02878 | E186: Replacement | F186: 1039 | G186: TRANSFER ARM STUCK
A187: 46206 | B187: Sai Anand Thevarmadam | C187: 77527 | D187: ZM1250940MEGO1059 | G187: DOUGHBALL NOT PRESSED
A188: 46206 | B188: Kanthimathi Santhikumar | C188: RSO07816 | D188: ZM1260102CAG08710 | E188: Replacement | F188: 182 | G188: TRANSFER ARM RATTLING NOISE
A189: 46206 | B189: Kanthimathi Santhikumar | C189: RSO07816 | D189: ZM1260102CAG08710 | E189: Replacement | F189: 182 | G189: TRANSFER ARM RATTLING NOISE
A190: 46206 | B190: Hemangi Patil | C190: 76744 | D190: ZM1260206CAG09277 | E190: Replacement | F190: 1288
A191: 46206 | B191: Rahul Mukerjee | C191: 63935 | D191: ZM1250624CAG00801 | E191: Replacement | F191: 406 | G191: NOT POWERING ON
A192: 46206 | B192: Rainee Saparia | C192: 77141 | D192: ZM1260102CAG08304 | E192: Replacement | F192: 50 | G192: TRANSFER ARM RATTLING NOISE
A193: 46206 | B193: Minakshi Gajera | C193: 74454 | D193: ZM1251042MEW01633 | E193: Parts Replacement | F193: 453 | G193: WRONG POWER CORD
A194: 46206 | B194: Pragya Rathore | C194: RSO05108 | D194: ZM1251043CAG03850 | E194: Replacement | F194: 135 | G194: NOT POWERING ON
A195: 46206 | B195: Dhruvi Patel | C195: 77111 | D195: ZM1260102CAG08535 | E195: Parts Replacement | F195: 402 | G195: DAMAGED KICKER
A196: 46206 | B196: Abhishek Sahadev Sutar | C196: 71305 | D196: ZM1251043CAG04147 | G196: TRANSFER ARM STUCK
A197: 46206 | B197: Ujjwal Kumar Behera | C197: 69642 | D197: ZM1250730MEG00590 | E197: Replacement | F197: 2
A198: 46206 | B198: Neetika Mittal | C198: 80736 | D198: ZM1260102CAG08684 | E198: Replacement | F198: 649 | G198: STUCK ON "PLEASE WAIT"
A199: 46206 | B199: Kanchan Bahirat | C199: 76521 | D199: ZM1251251CAG07837 | E199: Parts Replacement | F199: 580 | G199: DAMAGED KICKER
A200: 46206 | B200: Ram Boggarapu | C200: 74861 | D200: ZM1251250MEG02327 | E200: Parts Replacement | F200: 495 | G200: FLOUR CONTAINER AND KICKER MALFUNCTION
A201: 46206 | B201: Apurv Bhargava | C201: 76312 | D201: ZM1251251CAG07239 | E201: Replacement | F201: 496 | G201: TRANSFER ARM STUCK
A202: 46205 | B202: SEAN GEORGE | C202: 75628 | D202: ZM1251251CAG07224 | E202: Replacement | F202: 1488 | G202: PANS NOT HEATING
A203: 46205 | B203: Mugdha Naik | C203: 72140 | D203: ZM1251249MEW01910 | E203: Replacement | F203: 108 | G203: TRANSFER ARM STUCK
A204: 46205 | B204: Neha Seth | C204: 67260 | D204: ZM1250940MEG00997 | E204: Replacement | F204: 984 | G204: CANNOT TRANSFER DOUGHBALL
A205: 46205 | B205: Tushar Patel | C205: 78292 | D205: ZM1260311MEG03212 | G205: NOT POWERING ON
A206: 46205 | B206: Yogesh Kardak | C206: 71895 | D206: ZM1251042MEG01445 | E206: Replacement | F206: 2615 | G206: PRESS PAN STUCK
A207: 46205 | B207: Rajni Sidhu | C207: 79514 | D207: ZM1260311CAW09972 | E207: Replacement | F207: 118 | G207: NOT POWERING ON
A208: 46205 | B208: Sarika Nagawade | C208: 63582 | D208: ZM1250728MEG00357 | E208: Parts Replacement | G208: WATER CONTAINER AND KICKER ISSUE
...

Sheet FailureMapping
A1: Keyword | B1: Failure Mode | C1: Failure Category
A2: AESTHETICS | B2: Cosmetic Issue | C2: Others
A3: MACHINE NEVER WORKED OUT OF THE BOX | B3: DOA / Out of Box Failure | C3: Others
A4: FINAL CHECK STAGE AND DOES NOT PROCEED FURTHER | B4: Final Check Stage Stuck | C4: Others
A5: FIRMWARE AND HARDWARE ISSUE | B5: Firmware/Hardware Failure | C5: Others
A6: MACHINE STOPPED AFTER MAKING 1 ROTI | B6: Machine Performance Issue | C6: Others
A7: MACHINE PERFORMANCE | B7: Machine Performance Issue | C7: Others
A8: CLEANING BRUSH SHREDDING | B8: Cleaning Brush Damage | C8: Accessories
A9: SHREDDING BRUSH | B9: Cleaning Brush Damaged | C9: Accessories
A10: CLEANING BRUSH TO BE REPLACED | B10: Cleaning Brush Damaged | C10: Accessories
A11: APPROVED BY PARUL | B11: Approved by Support | C11: Administrative
A12: CHECKED AND APPROVED BY ENGINEERS | B12: Administrative Note | C12: Administrative
... A680: DB WEIGHT DETECTION WARNING | B680: DB Detection Warning | C680: VT Module

Sheet Odoo
A1: Issue Reported Date | B1: Customer's Name | C1: Order# | D1: MachineSerialNumber | E1: Replacement Type | F1: Roti Count | G1: Return Type | H1: Replacement SO | I1: Status | J1: RMA Lines | K1: Fee Amount | L1: Is Shipment Initiated | M1: SO Return Status | N1: Notes | O1: Notes_Clean
A2: 46237 | B2: Sujith Vijaya Kumar | C2: 74081 | D2: ZM1251250CAW06644 | E2: Machine | F2: 875 | G2: Replacement | H2: RSO09356 | I2: Processing | J2: [ZNF0111AW-CA] Rotimatic Next (Black & White) | K2: 39.807884 | L2: 1 | M2: Return with Refund/Replacement | N2: ZM1251250CAW06644 roti count: 875 Kneading Tray Stuck issue | O2: ZM1251250CAW06644 ROTI COUNT:: 875 KNEADING TRAY STUCK ISSUE
A3: 46237 | B3: Shalaka Sawant | C3: 75980 | D3: ZM1251251CAG07710 | E3: Machine | F3: 116 | G3: Replacement | H3: RSO09355 | I3: Processing | J3: [ZNF0111AG-CA] Rotimatic Next (Black & Grey) | K3: 0 | L3: 1 | M3: Return with Refund/Replacement | N3: ZM1251251CAG07710 roti count: 116 Transfer Arm rattling noise issue | O3: ZM1251251CAG07710 ROTI COUNT:: 116 TRANSFER ARM RATTLING NOISE ISSUE
A4: 46237 | B4: Neel Shah | C4: RSO03202 | D4: ZM1250729CAG01563 | E4: Machine | F4: 0 | G4: Replacement | H4: RSO09354 | I4: Processing | J4: [ZNF0111AG-CA] Rotimatic Next (Black & Grey) | K4: 0 | L4: 1 | M4: Return with Refund/Replacement | N4: ZM1250729CAG01563 roti count: 0 Knead Blade Stuck | O4: ZM1250729CAG01563 ROTI COUNT:: 0 KNEADER BLADE STUCK
A5: 46237 | B5: Owais Ahmed | C5: RSO05154 | D5: ZM1251146MEG01650 | E5: Machine | F5: 963 | G5: Replacement | H5: RSO09353 | I5: Processing | J5: [ZNF0111AG-ME] Rotimatic Next (Black & Grey) | K5: 0 | L5: 1 | M5: Return with Refund/Replacement | N5: ZM1251146MEG01650 roti count: 963 Cannot Transfer Doughball | O5: ZM1251146MEG01650 ROTI COUNT:: 963 CANNOT TRANSFER DOUGH BALL
A6: 46237 | B6: Saurabh Brahmbhatt | C6: 41090 | D6: ZM82308CAB139 | E6: Machine | F6: 8500 | G6: Replacement | H6: RSO09352 | I6: Processing | J6: [ZMA0111A-CA] Rotimatic Plus | K6: 0 | L6: 1 | M6: Return with Refund/Replacement | N6: ZM82308CAB139 roti count: 8500 Roller is not Moving | O6: ZM82308CAB139 ROTI COUNT:: 8500 ROLLER IS NOT MOVING
A7: 46237 | B7: Pranjal Jain | C7: RSO04838 | D7: ZM1251144CAW04488 | E7: Machine | F7: 609 | G7: Replacement | H7: RSO09351 | I7: Processing | J7: [ZNF0111AW-CA] Rotimatic Next (Black & White) | K7: 0 | L7: 1 | M7: Return with Refund/Replacement | N7: ZM1251144CAW04488 roti count: 609 Not powering on | O7: ZM1251144CAW04488 ROTI COUNT:: 609 NOT NOT POWERING ON
A8: 46234 | B8: Ashish Mehta | C8: 78106 | D8: ZM1260102CAG08113 | E8: Machine | F8: 433 | G8: Replacement | H8: RSO09350 | I8: Processing | J8: [ZNF0111AG-CA] Rotimatic Next (Black & Grey) | K8: 0 | L8: 1 | M8: Return with Refund/Replacement | N8: ZM1260102CAG08113 roti count: 433 Not powering on | O8: ZM1260102CAG08113 ROTI COUNT:: 433 NOT NOT POWERING ON
A9: 46234 | B9: Rohit Yadav | C9: 62977 | D9: ZM1250416CAG00186 | E9: Machine | F9: 712 | G9: Replacement | H9: RSO09349 | I9: Processing | J9: [ZMA0111A-CA] Rotimatic Plus | K9: 0 | L9: 1 | M9: Return with Refund/Replacement | N9: ZM1250416CAG00186 roti count: 712 Transfer Arm Stuck | O9: ZM1250416CAG00186 ROTI COUNT:: 712 TRANSFER ARM STUCK
A10: 46234 | B10: Brigade People Pty Ltd | C10: 68935 | D10: ZM1250835MEW00868 | E10: Machine | F10: 0 | G10: Replacement | H10: RSO09348 | I10: Processing | J10: [ZNF0111AW-ME] Rotimatic Next (Black & White) | K10: 172.46627 | L10: 1 | M10: Return with Refund/Replacement | N10: ZM1250835MEW00868 roti count: 0 Knead Blade Stuck | O10: ZM1250835MEW00868 ROTI COUNT:: 0 KNEADER BLADE STUCK
A11: 46234 | B11: sateesh vadde | C11: 71143 | D11: ZM1251043CAG03935 | E11: Machine | F11: 0 | G11: Replacement | H11: RSO09347 | I11: Processing | J11: [ZNF0111AG-CA] Rotimatic Next (Black & Grey) | K11: 211.14687 | L11: 1 | M11: Return with Refund/Replacement | N11: ZM1251043CAG03935 roti count: 0 Transfer Arm Stuck | O11: ZM1251043CAG03935 ROTI COUNT:: 0 TRANSFER ARM STUCK
A12: 46234 | B12: Ashleye Soanes | C12: 80569 | D12: ZM1260311CAW09995 | E12: Machine | F12: 0 | G12: Replacement | H12: RSO09346 | I12: Processing | J12: [ZNF0111AW-CA] Rotimatic Next (Black & White) | K12: 54.064898 | L12: 1 | M12: Return with Refund/Replacement | N12: ZM1260311CAW09995 roti count: 0 Transfer Arm Stuck | O12: ZM1260311CAW09995 ROTI COUNT:: 0 TRANSFER ARM STUCK
A13: 46234 | B13: varun_varmani@hotmail.com | C13: 76496 | D13: ZM1260209MEG03101 | E13: Machine | F13: 0 | G13: Replacement | H13: RSO09345 | I13: Processing | J13: [2YearRotimaticNextRotimaticCareWarranty] Rotimatic Next - Rotimatic Care Plus Warranty - 2 Years | K13: 124.93907 | L13: 1 | M13: Return with Refund/Replacement | N13: ZM1260209MEG03101 roti count: 0 Transfer Arm Stuck | O13: ZM1260209MEG03101 ROTI COUNT:: 0 TRANSFER ARM STUCK
... A19: 46234 | B19: Munish Minocha | C19: 79729 | D19: ZM1260311CAW09988 | E19: Machine | F19: 0 | G19: Replacement | H19: RSO09339 | I19: Processing | J19: [ZNF0111AW-CA] Rotimatic Next (Black & White) | K19: 48.332764 | L19: 1 | M19: Return with Refund/Replacement | N19: ZM1260311CAW09988 roti count: 0 Not Powering On | O19: ZM1260311CAW09988 ROTI COUNT:: 0 NOT NOT POWERING ON
A20: 46233 | B20: vidhi modi | C20: 70306 | D20: ZM1251043CAG03932 | G20: Refund with Return | I20: Submitted | J20: [6MonthsRotimaticNextRotimaticCareWarranty] Rotimatic Next - Rotimatic Care Plus Warranty - 6 Months | K20: 0 | L20: 1 | M20: Cancellation | N20: Current Machine Serial Number: ZM1251043CAG03932 Roti Count: Unable to check the tool is not working Main Issue: Machine Related Issue Type: Not powering ON Replacement Received Count: 0 Troubleshooting Done: Y Tech Agent Name Handled: Meenakshi C Call handled by Raja Ravi Verma | O20: CURRENT MACHINE NUMBER ZM1251043CAG03932 ROTI COUNT:: UNABLE TO CHECK THE TOOL IS NOT WORKING MAIN ISSUE: MACHINE RELATED ISSUE TYPE: NOT NOT POWERING ON REPLACEMENT RECEIVED COUNT: 0 TROUBLESHOOTING DONE: Y TECH AGENT NAME HANDLED: MEENAKSHI C CALL HANDLED BY RAJA RAVI VERMA
A21: 46233 | B21: Sayali Autade | C21: 74763 | D21: ZM1251250CAW06779 | E21: Machine | F21: 1914 | G21: Replacement | H21: RSO09338 | I21: Processing | J21: [2YearRotimaticNextRotimaticCareWarranty] Rotimatic Next - Rotimatic Care Plus Warranty - 2 Years | K21: 40.323754 | L21: 1 | M21: Return with Refund/Replacement | N21: ZM1251250CAW06779 roti count: 1914 Kneading Tray Stuck | O21: ZM1251250CAW06779 ROTI COUNT:: 1914 KNEADING TRAY STUCK
A22: 46233 | B22: Alakh Biniwale | C22: 71777 | D22: ZM1251146CAG04887 | E22: Machine | F22: 0 | G22: Replacement | H22: RSO09337 | I22: Processing | J22: [3YearRotimaticNextRotimaticCareWarranty] Rotimatic Next - Rotimatic Care Plus Warranty - 3 Years | K22: 63.221368 | L22: 1 | M22: Return with Refund/Replacement | N22: ZM1251146CAG04887 roti count: 0 Top Casing Crack | O22: ZM1251146CAG04887 ROTI COUNT:: 0 TOP CASING CRACK
A23: 46233 | B23: Anmol Singh | C23: RSO04577 | D23: ZM1250940CAW03285 | E23: Machine | F23: 0 | G23: Replacement | H23: RSO09336 | I23: Processing | J23: [ZNF0111AG-CA] Rotimatic Next (Black & Grey) | K23: 0 | L23: 1 | M23: Return with Refund/Replacement | N23: ZM1250940CAW03285 roti count: 0 Not Powering On | O23: ZM1250940CAW03285 ROTI COUNT:: 0 NOT NOT POWERING ON
A24: 46232 | B24: Shipra Singh | C24: RSO05912 | D24: ZM1251250CAW06647 | E24: Machine | F24: 48 | G24: Replacement | H24: RSO09335 | I24: Processing | J24: [ZNF0111AW-CA] Rotimatic Next (Black & White) | K24: 0 | L24: 1 | M24: Return with Refund/Replacement | N24: ZM1251250CAW06647 roti count: 48 Kneader Gear making Noise | O24: ZM1251250CAW06647 ROTI COUNT:: 48 KNEADER GEAR MAKING NOISE
A25: 46232 | B25: Ajay Sekhri | C25: 64218 | D25: ZM1250626CAW01396 | E25: Machine | F25: 230 | G25: Replacement | H25: RSO09334 | I25: Processing | J25: [3YearRotimaticNextRotimaticCareWarranty] Rotimatic Next - Rotimatic Care Plus Warranty - 3 Years | K25: 0 | L25: 1 | M25: Return with Refund/Replacement | N25: ZM1250626CAW01396 roti count: 230 Kneading Tray Stuck | O25: ZM1250626CAW01396 ROTI COUNT:: 230 KNEADING TRAY STUCK
A26: 46232 | B26: Abhishek Dhoundiyal | C26: RSO08422 | D26: ZM1260417CAG10464 | E26: Machine | F26: 305 | G26: Replacement | H26: RSO09333 | I26: Processing | J26: [ZNF0111AG-CA] Rotimatic Next (Black & Grey) | K26: 0 | L26: 1 | M26: Return with Refund/Replacement | N26: ZM1260417CAG10464 roti count: 305 Transfer Arm Rattling Noise | O26: ZM1260417CAG10464 ROTI COUNT:: 305 TRANSFER ARM RATTLING NOISE
A27: 46231 | B27: Shekar datt maharaj | C27: 81420 | D27: ZM1251250MEG02403 | F27: 128 | G27: Refund with Return | I27: Submitted | J27: [ZNF0111AG-ME] Rotimatic Next (Black & Grey) | K27: 65.31 | L27: 1 | M27: Cancellation | N27: Current Machine Serial Number: ZM1251250MEG02403 Roti Count: 128 Main Issue: Machine Related Issue Type: (Failure Modes): Transfer Arm stuck Replacement Received Count: 0 Troubleshooting Done: Y/N: Y Tech Agent Name Handled: Deepalakshmi | O27: CURRENT MACHINE NUMBER ZM1251250MEG02403 ROTI COUNT:: 128 MAIN ISSUE: MACHINE RELATED ISSUE TYPE: (FAILURE MODES): TRANSFER ARM STUCK REPLACEMENT RECEIVED COUNT: 0 TROUBLESHOOTING DONE: Y/N: Y TECH AGENT NAME HANDLED: DEEPALAKSHMI
A28: 46231 | B28: Rahiman Mohammad | C28: 69178 | D28: ZM1250835CAG02569 | E28: Machine | F28: 1638 | G28: Replacement | H28: RSO09332 | I28: Processing | J28: [ZNF0111AG-CA] Rotimatic Next (Black & Grey) | K28: 196.50642 | L28: 1 | M28: Return with Refund/Replacement | N28: ZM1250835CAG02569 roti count: 1638 Knead Blade Stuck | O28: ZM1250835CAG02569 ROTI COUNT:: 1638 KNEADER BLADE STUCK
A29: 46231 | B29: Suchithra Gopinath | C29: 71894 | D29: ZM1251144CAG04882 | E29: Part | F29: 1042 | G29: Replacement | H29: RSO09331 | I29: Closed | J29: [2YearRotimaticNextRotimaticCareWarranty] Rotimatic Next - Rotimatic Care Plus Warranty - 2 Years | K29: 43.06 | L29: 1 | M29: Return with Refund/Replacement | N29: ZM1251144CAG04882 Roti Count 1042 Damaged Kicker | O29: ZM1251144CAG04882 ROTI COUNT: 1042 DAMAGED KICKER
A30: 46231 | B30: Vijay Subramanyam | C30: 76268 | D30: ZM1251251CAG07726 | F30: 2 | G30: Refund with Return | I30: Submitted | J30: [ZNF0111AG-CA] Rotimatic Next (Black & Grey) | K30: 34.94 | L30: 1 | M30: Cancellation | N30: Current Machine Serial Number: ZM1251251CAG07726 Roti Count: 2 Main Issue: Machine Related Issue Type: (Failure Modes): Water leakage Replacement Received Count: 0 Troubleshooting Done: Y/N: Y Tech Agent Name Handled: NA | O30: CURRENT MACHINE NUMBER ZM1251251CAG07726 ROTI COUNT:: 2 MAIN ISSUE: MACHINE RELATED ISSUE TYPE: (FAILURE MODES): WATER LEAKAGE REPLACEMENT RECEIVED COUNT: 0 TROUBLESHOOTING DONE: Y/N: Y TECH AGENT NAME HANDLED: NA
A31: 46231 | B31: ILango Marag | C31: 74743 | D31: ZM1251251CAG07419 | E31: Machine | F31: 756 | G31: Replacement | H31: RSO09330 | I31: Processing | J31: [ZNF0111AG-CA] Rotimatic Next (Black & Grey) | K31: 0 | L31: 1 | M31: Return with Refund/Replacement | N31: ZM1251251CAG07419 roti count: 756 Transfer Arm Rattling Noise | O31: ZM1251251CAG07419 ROTI COUNT:: 756 TRANSFER ARM RATTLING NOISE
A32: 46231 | B32: Chetan Pachchhao | C32: RSO06651 | D32: ZM1260208CAG09764 | E32: Machine | F32: 298 | G32: Replacement | H32: RSO09329 | I32: Processing | J32: [ZNF0111AG-CA] Rotimatic Next (Black & Grey) | K32: 0 | L32: 1 | M32: Return with Refund/Replacement | N32: ZM1260208CAG09764 roti count: 298 Kneading Motor Making Noise | O32: ZM1260208CAG09764 ROTI COUNT:: 298 KNEADING MOTOR MAKING NOISE
A33: 46231 | B33: Ritika Kureti | C33: RSO02801 | D33: ZM1250415CAG00126 | E33: Machine | F33: 0 | G33: Replacement | H33: RSO09328 | I33: Processing | J33: [ZNF0111AG-CA] Rotimatic Next (Black & Grey) | K33: 0 | L33: 1 | M33: Return with Refund/Replacement | N33: ZM1250415CAG00126 roti count: 0 kneading motor issue | O33: ZM1250415CAG00126 ROTI COUNT:: 0 KNEADING MOTOR ISSUE
A34: 46230 | B34: Sana Chaudhry | C34: 72664 | D34: ZM1251146CAG05219 | E34: Machine | F34: 667 | G34: Replacement | H34: RSO09308 | I34: Processing | J34: [ZNF0111AG-CA] Rotimatic Next (Black & Grey) | K34: 0 | L34: 1 | M34: Return with Refund/Replacement | N34: ZM1251146CAG05219 roti count: 667 Not Powering On | O34: ZM1251146CAG05219 ROTI COUNT:: 667 NOT NOT POWERING ON
A35: 46230 | B35: Zebra Khan | C35: 68800 | D35: ZM1251042MEW01583 | E35: Machine | F35: 0 | G35: Replacement | H35: RSO09299 | I35: Processing | J35: [3YearRotimaticNextRotimaticCareWarranty] Rotimatic Next - Rotimatic Care Plus Warranty - 3 Years | K35: 153.47404 | L35: 1 | M35: Return with Refund/Replacement | N35: ZM1251042MEW01583 roti count: 0 Transfer Arm Stuck | O35: ZM1251042MEW01583 ROTI COUNT:: 0 TRANSFER ARM STUCK
A36: 46230 | B36: Nikita Pawar | C36: 78099 | D36: ZM1260311MEG03178 | E36: Machine | F36: 43 | G36: Replacement | H36: RSO09327 | I36: Processing | J36: [3YearRotimaticNextRotimaticCareWarranty] Rotimatic Next - Rotimatic Care Plus Warranty - 3 Years | K36: 0 | L36: 1 | M36: Return with Refund/Replacement | N36: ZM1260311MEG03178 roti count: 43 Damaged part inside the machine | O36: ZM1260311MEG03178 ROTI COUNT:: 43 DAMAGED PART INSIDE THE MACHINE
A37: 46230 | B37: Shambhavi Mohan | C37: 55085 | D37: ZM82405CAB00E | E37: Machine | F37: 2934 | G37: Replacement | H37: RSO09326 | I37: Processing | J37: [Extend-Protection-Plan-299.00] Extend Protection Plan - US - 2 Years (299.00) | K37: 39.757997 | L37: 1 | M37: Return with Refund/Replacement | N37: ZM82405CAB00E roti count:2934 Final Check stage and does not proceed further. | O37: ZM82405CAB00E ROTI COUNT::2934 FINAL CHECK STAGE AND DOES NOT PROCEED FURTHER.
A38: 46230 | B38: Tarun Kalyani | C38: 67400 | D38: ZM1250940MEG01005 | E38: Part | F38: 523 | G38: Replacement | H38: RSO09325 | I38: Closed | J38: [ZNF0111AG-ME] Rotimatic Next (Black & Grey) | K38: 0 | L38: 1 | M38: Return with Refund/Replacement | N38: ZM1250940MEG01005 Roti Count 523 Damaged Kicker | O38: ZM1250940MEG01005 ROTI COUNT: 523 DAMAGED KICKER
A39: 46230 | B39: Pavan Reddy | C39: 69167 | D39: ZM125940MEG00998 | E39: Machine | F39: 0 | G39: Replacement | H39: RSO09324 | I39: Processing | J39: [ZNF0111AG-ME] Rotimatic Next (Black & Grey) | K39: 0 | L39: 1 | M39: Return with Refund/Replacement | N39: ZM125940MEG00998 roti count: 0 Cannot Transfer Doughball | O39: ZM125940MEG00998 ROTI COUNT:: 0 CANNOT TRANSFER DOUGH BALL
A40: 46230 | B40: Manoj Deshpande | C40: 72199 | D40: ZM1251146CAW5311 | E40: Machine | F40: 780 | G40: Replacement | H40: RSO09323 | I40: Processing | J40: [2YearRotimaticNextRotimaticCareWarranty] Rotimatic Next - Rotimatic Care Plus Warranty - 2 Years | K40: 45.961334 | L40: 1 | M40: Return with Refund/Replacement | N40: ZM1251146CAW5311 roti count: 780 Kneader Tray Stuck | O40: ZM1251146CAW5311 ROTI COUNT:: 780 KNEADER TRAY STUCK
A41: 46230 | B41: Anuj Shah | C41: 71490 | D41: ZM1250940CAWO3534 | E41: Machine | F41: 0 | G41: Replacement | H41: RSO09322 | I41: Processing | J41: [ZNF0111AW-CA] Rotimatic Next (Black & White) | K41: 227.40313 | L41: 1 | M41: Return with Refund/Replacement | N41: ZM1250940CAWO3534 roti count: 0 Kneader Tray Stuck | O41: ZM1250940CAWO3534 ROTI COUNT:: 0 KNEADER TRAY STUCK
A42: 46230 | B42: Aditya Malkar | C42: 72321 | D42: ZM1251249MEW01927 | E42: Machine | F42: 723 | G42: Replacement | H42: RSO09321 | I42: Processing | J42: [ZNF0111AW-ME] Rotimatic Next (Black & White) | K42: 0 | L42: 1 | M42: Return with Refund/Replacement | N42: ZM1251249MEW01927 roti count: 723 Loadcell error/Black spots on the LCD Screen | O42: ZM1251249MEW01927 ROTI COUNT:: 723 LOADCELL ERROR/BLACK SPOTROUBLESHOOTING ON THE LCD SCREEN
... A61: 46230 | B61: Dhaval Rana | C61: 71252 | D61: ZM1251041MEG01287 | E61: Machine | F61: 22 | G61: Replacement | H61: RSO09300 | I61: Processing | J61: [3YearRotimaticNextRotimaticCareWarranty] Rotimatic Next - Rotimatic Care Plus Warranty - 3 Years | K61: 128.61124 | L61: 1 | M61: Return with Refund/Replacement | N61: ZM1251041MEG01287 roti count: 22 Transfer Arm Stuck | O61: ZM1251041MEG01287 ROTI COUNT:: 22 TRANSFER ARM STUCK
A62: 46230 | B62: Shreya Srivastava | C62: 79409 | D62: ZM1260417CAG10187 | F62: 166 | G62: Refund with Return | I62: Submitted | J62: [ZNF0111AG-CA] Rotimatic Next (Black & Grey) | K62: 0 | L62: 1 | M62: Cancellation | N62: Current Machine Serial Number:ZM1260417CAG10187 Roti Count:166 Main Issue: Machine Related Issue Type:-tThe machine began producing a loud mechanical noise whenever the dough catcher mechanism moved backward and forward. The customer stated that the door catcher would stop midway and fail to latch the door correctly, eventually causing the machine to stop functioning completely. Replacement Received Count:0 Troubleshooting Done: Y Tech Agent Name Handled: Nisarga | O62: CURRENT MACHINE NUMBERZM1260417CAG10187 ROTI COUNT::166 MAIN ISSUE: MACHINE RELATED ISSUE TYPE:-TTHE MACHINE BEGAN PRODUCING A LOUD MECHANICAL NOISE WHENEVER THE DOUGH KICKER MECHANISM MOVED BACKWARD AND FORWARD. THE CUSTOMER STATED THAT THE DOOR CATCHER WOULD STOP MIDWAY AND FAIL TO LATCH THE DOOR CORRECTLY, EVENTUALLY CAUSING THE MACHINE TO STOP FUNCTIONING COMPLETELY. REPLACEMENT RECEIVED COUNT:0 TROUBLESHOOTING DONE: Y TECH AGENT NAME HANDLED: NISARGA
A63: 46230 | B63: sanjeet sahu | C63: RSO07338 | D63: ZM1260102CAG08456 | E63: Machine | F63: 0 | G63: Replacement | H63: RSO09298 | I63: Processing | J63: [ZNF0111AG-CA] Rotimatic Next (Black & Grey) | K63: 0 | L63: 1 | M63: Return with Refund/Replacement | N63: ZM1260102CAG08456 roti count: 0 Not powering on | O63: ZM1260102CAG08456 ROTI COUNT:: 0 NOT NOT POWERING ON
A64: 46230 | B64: Dipti Amlani | C64: 67687 | D64: ZM1250727MEW00221 | E64: Machine | F64: 907 | G64: Replacement | H64: RSO09297 | I64: Processing | J64: [ZNF0111AW-ME] Rotimatic Next (Black & White) | K64: 149.55879 | L64: 1 | M64: Return with Refund/Replacement | N64: ZM1250727MEW00221 roti count: 907 Rattling Noise | O64: ZM1250727MEW00221 ROTI COUNT:: 907 RATTLING NOISE
A65: 46230 | B65: HARSHA B REDDY | C65: 71348 | D65: ZM1251144CAG04802 | E65: Machine | F65: 272 | G65: Replacement | H65: RSO09296 | I65: Processing | J65: [ZNF0111AG-CA] Rotimatic Next (Black & Grey) | K65: 44.083644 | L65: 1 | M65: Return with Refund/Replacement | N65: ZM1251144CAG04802 roti count: 272 Transfer Arm Stuck | O65: ZM1251144CAG04802 ROTI COUNT:: 272 TRANSFER ARM STUCK
A66: 46230 | B66: SIDDHARTHA SINGH | C66: 64533 | D66: ZM1250625CAG01107 | E66: Machine | F66: 0 | G66: Replacement | H66: RSO09295 | I66: Processing | J66: [ZNF0111AG-CA] Rotimatic Next (Black & Grey) | K66: 0 | L66: 1 | M66: Return with Refund/Replacement | N66: ZM1250625CAG01107 roti count: 0 Not powering on | O66: ZM1250625CAG01107 ROTI COUNT:: 0 NOT NOT POWERING ON
A67: 46230 | B67: Lakhshya Bansal | C67: RSO07389 | D67: ZM1260102CAG08337 | E67: Machine | F67: 279 | G67: Replacement | H67: RSO09294 | I67: Processing | J67: [ZNF0111AG-CA] Rotimatic Next (Black & Grey) | K67: 0 | L67: 1 | M67: Return with Refund/Replacement | N67: ZM1260102CAG08337 roti count: 279 Transfer Arm Stuck | O67: ZM1260102CAG08337 ROTI COUNT:: 279 TRANSFER ARM STUCK
A68: 46230 | B68: Nikita Rasam | C68: 64429 | D68: ZM12512CAG06370 | E68: Machine | F68: 0 | G68: Replacement | H68: RSO09293 | I68: Processing | J68: [ZNF0111AW-CA] Rotimatic Next (Black & White) | K68: 0 | L68: 1 | M68: Return with Refund/Replacement | N68: ZM12512CAG06370 roti count: 0 kneading motor rotator broken | O68: ZM12512CAG06370 ROTI COUNT:: 0 KNEADING MOTOR ROTIATOR BROKEN
A69: 46230 | B69: Shabbir Bharmal | C69: 77793 | D69: ZM1260208CAG09684 | E69: Machine | F69: 135 | G69: Replacement | H69: RSO09291 | I69: Processing | J69: [3YearRotimaticNextRotimaticCareWarranty] Rotimatic Next - Rotimatic Care Plus Warranty - 3 Years | K69: 52.102381 | L69: 1 | M69: Return with Refund/Replacement | N69: ZM1260208CAG09684 roti count: 135 Not powering on | O69: ZM1260208CAG09684 ROTI COUNT:: 135 NOT NOT POWERING ON
A70: 46230 | B70: Beni Verma | C70: 78084 | D70: ZM1260104CAW08928 | E70: Machine | F70: 20 | G70: Replacement | H70: RSO09289 | I70: Processing | J70: [ZNF0111AW-CA] Rotimatic Next (Black & White) | K70: 35.669564 | L70: 1 | M70: Return with Refund/Replacement | N70: ZM1260104CAW08928 roti count: 20 Not powering on | O70: ZM1260104CAW08928 ROTI COUNT:: 20 NOT NOT POWERING ON
A71: 46230 | B71: Neeraj Vig | C71: 70740 | D71: ZM1251144CAG04302 | E71: Machine | F71: 2250 | G71: Replacement | H71: RSO09288 | I71: Processing | J71: [ZNF0111AG-CA] Rotimatic Next (Black & Grey) | K71: 53.493351 | L71: 1 | M71: Return with Refund/Replacement | N71: ZM1251144CAG04302 roti count: 2250 Transfer Arm Rattling Noise | O71: ZM1251144CAG04302 ROTI COUNT:: 2250 TRANSFER ARM RATTLING NOISE
A72: 46230 | B72: Sunil Biswal | C72: 65050 | D72: ZM1250627MEG00198 | E72: Machine | F72: 788 | G72: Replacement | H72: RSO09287 | I72: Processing | J72: [ZNF0111AG-ME] Rotimatic Next (Black & Grey) | K72: 84.847627 | L72: 1 | M72: Return with Refund/Replacement | N72: ZM1250627MEG00198 roti count: 788 Broken Stirrer | O72: ZM1250627MEG00198 ROTI COUNT:: 788 STIRRER NOT ROTATING
A73: 46230 | B73: Shweta Patel | C73: 78328 | D73: ZM1260209MEG02957 | E73: Machine | F73: 1291 | G73: Replacement | H73: RSO09286 | I73: Processing | J73: [2YearRotimaticNextRotimaticCareWarranty] Rotimatic Next - Rotimatic Care Plus Warranty - 2 Years | K73: 0 | L73: 1 | M73: Return with Refund/Replacement | N73: ZM1260209MEG02957 roti count: 1291 Cannot Transfer Doughball | O73: ZM1260209MEG02957 ROTI COUNT:: 1291 CANNOT TRANSFER DOUGH BALL
A74: 46230 | B74: Unmesh Vhatkar | C74: RSO05798 | D74: ZM1251249CAG06299 | E74: Machine | F74: 2035 | G74: Replacement | H74: RSO09285 | I74: Processing | J74: [ZNF0111AG-CA] Rotimatic Next (Black & Grey) | K74: 0 | L74: 1 | M74: Return with Refund/Replacement | N74: ZM1251249CAG06299 roti count: 2035 Cannot Transfer Doughball | O74: ZM1251249CAG06299 ROTI COUNT:: 2035 CANNOT TRANSFER DOUGH BALL
... A87: 46227 | B87: punit solanki | C87: RSO06956 | D87: ZM1260104CAW08818 | E87: Machine | F87: 50 | G87: Replacement | H87: RSO09026 | I87: Processing | J87: [ZNF0111AW-CA] Rotimatic Next (Black & White) | K87: 0 | L87: 1 | M87: Return with Refund/Replacement | N87: ZM1260104CAW08818 roti count: 50 Not powering on | O87: ZM1260104CAW08818 ROTI COUNT:: 50 NOT NOT POWERING ON
A88: 46227 | B88: Jasleen Kaur | C88: 69905 | D88: ZM1260104CAW08810 | F88: 0 | G88: Refund with Return | I88: Submitted | J88: [1YearRotimaticNextRotimaticCareWarranty] Rotimatic Next - Rotimatic Care Plus Warranty - 1 Year | K88: 46.13 | L88: 1 | M88: Cancellation | N88: Current Machine Serial Number: ZM1260104CAW08810 Roti Count: 0 Main Issue: Machine Related Issue Type: (Failure Modes): Pan stuck Replacement Received Count: 2 Troubleshooting Done: Y/N: Y Tech Agent Name Handled: Mohammad Asrar | O88: CURRENT MACHINE NUMBER ZM1260104CAW08810 ROTI COUNT:: 0 MAIN ISSUE: MACHINE RELATED ISSUE TYPE: (FAILURE MODES): PAN STUCK REPLACEMENT RECEIVED COUNT: 2 TROUBLESHOOTING DONE: Y/N: Y TECH AGENT NAME HANDLED: MOHAMMAD ASRAR
A89: 46227 | B89: Sohan Nipunage | C89: 83079 | D89: ZM1260417CAW10481 | E89: Machine | F89: 307 | G89: Replacement | I89: Submitted | J89: [2YearRotimaticNextRotimaticCareWarranty] Rotimatic Next - Rotimatic Care Plus Warranty - 2 Years | K89: 0 | L89: 1 | M89: Return with Refund/Replacement | N89: ZM1260417CAW10481 roti count: 307 Transfer Arm Stuck | O89: ZM1260417CAW10481 ROTI COUNT:: 307 TRANSFER ARM STUCK
A90: 46227 | B90: Ahmed Khattak | C90: 66952 | D90: ZM1250728MEG00411 | E90: Machine | F90: 0 | G90: Replacement | H90: RSO09049 | I90: Processing | J90: [ZNF0111AG-ME] Rotimatic Next (Black & Grey) | K90: 168.01606 | L90: 1 | M90: Return with Refund/Replacement | N90: ZM1250728MEG00411 roti count: 00 Dispensing Position Not Correct | O90: ZM1250728MEG00411 ROTI COUNT:: 00 DISPENSING POSITION NOT CORRECT
A91: 46227 | B91: Akarsh Singh | C91: 64583 | D91: ZM1250730MEG00566 | E91: Machine | F91: 526 | G91: Replacement | H91: RSO08974 | I91: Processing | J91: [ZMA0111A-ME] Rotimatic Plus | K91: 94.414529 | L91: 1 | M91: Return with Refund/Replacement | N91: ZM1250730MEG00566 roti count: 526 Stirrer Not Rotating | O91: ZM1250730MEG00566 ROTI COUNT:: 526 STIRRER NOT ROTATING
A92: 46227 | B92: Aditya Bhambhu | C92: RSO07820 | D92: ZM1260417CAW10417 | E92: Machine | F92: 2104 | G92: Replacement | H92: RSO09050 | I92: Processing | J92: [ZNF0111AW-CA] Rotimatic Next (Black & White) | K92: 0 | L92: 1 | M92: Return with Refund/Replacement | N92: ZM1260417CAW10417 roti count: 2104 Cannot Transfer Doughball | O92: ZM1260417CAW10417 ROTI COUNT:: 2104 CANNOT TRANSFER DOUGH BALL
A93: 46227 | B93: Vaama Patel | C93: 77736 | D93: ZM1260102CAG08499 | E93: Machine | F93: 183 | G93: Replacement | I93: Submitted | J93: [ZNF0111AG-CA] Rotimatic Next (Black & Grey) | K93: 37.127093 | L93: 1 | M93: Return with Refund/Replacement | N93: ZM1260102CAG08499 roti count: 183 Kneader Tray Stuck | O93: ZM1260102CAG08499 ROTI COUNT:: 183 KNEADER TRAY STUCK
A94: 46227 | B94: Vineet Mehra | C94: 68091 | D94: ZM1250731CAG01910 | E94: Machine | F94: 76 | G94: Replacement | I94: Submitted | J94: [ZNF0111AG-CA] Rotimatic Next (Black & Grey) | K94: 58.669978 | L94: 1 | M94: Return with Refund/Replacement | N94: ZM1250731CAG01910 roti count: 76 Knead Blade Stuck | O94: ZM1250731CAG01910 ROTI COUNT:: 76 KNEADER BLADE STUCK
A95: 46227 | B95: Vibha Vig | C95: RSO05068 | D95: ZM1251144CAW04359 | E95: Machine | F95: 479 | G95: Replacement | I95: Submitted | J95: [ZNF0111AW-CA] Rotimatic Next (Black & White) | K95: 0 | L95: 1 | M95: Return with Refund/Replacement | N95: ZM1251144CAW04359 roti count: 479 Not Powering On | O95: ZM1251144CAW04359 ROTI COUNT:: 479 NOT NOT POWERING ON
A96: 46227 | B96: Anjushma Sharma | C96: 78169 | D96: ZM1260209MEG03025 | E96: Machine | F96: 570 | G96: Replacement | I96: Submitted | J96: [3YearRotimaticNextRotimaticCareWarranty] Rotimatic Next - Rotimatic Care Plus Warranty - 3 Years | K96: 0 | L96: 1 | M96: Return with Refund/Replacement | N96: ZM1260209MEG03025 roti count: 570 Transfer Arm Rattling Noise | O96: ZM1260209MEG03025 ROTI COUNT:: 570 TRANSFER ARM RATTLING NOISE
A97: 46227 | B97: Sarika Dawar | C97: RSO06183 | D97: ZM1251251CAG06824 | E97: Machine | F97: 1835 | G97: Replacement | I97: Submitted | J97: [ZNF0111AG-CA] Rotimatic Next (Black & Grey) | K97: 0 | L97: 1 | M97: Return with Refund/Replacement | N97: ZM1251251CAG06824 roti count: 1835 Slave Communication Error | O97: ZM1251251CAG06824 ROTI COUNT:: 1835 SLAVE COMMUNICATION ERROR
A98: 46227 | B98: Shailendra Kontham | C98: RSO05431 | D98: ZM1251146CAG05336 | E98: Machine | F98: 670 | G98: Replacement | I98: Submitted | J98: [ZNF0111AG-CA] Rotimatic Next (Black & Grey) | K98: 0 | L98: 1 | M98: Return with Refund/Replacement | N98: ZM1251146CAG05336 roti count: 670 DB Detection Warning | O98: ZM1251146CAG05336 ROTI COUNT:: 670 DB DETECTION WARNING
A99: 46227 | B99: Vishal Saraf | C99: 76393 | D99: ZM1260206MEG02551 | E99: Machine | F99: 639 | G99: Replacement | I99: Submitted | J99: [ZNF0111AG-ME] Rotimatic Next (Black & Grey) | K99: 78.125173 | L99: 1 | M99: Return with Refund/Replacement | N99: ZM1260206MEG02551 roti count: 639 Transfer Arm Stuck | O99: ZM1260206MEG02551 ROTI COUNT:: 639 TRANSFER ARM STUCK
A100: 46227 | B100: Amol Parkhe | C100: 68728 | D100: ZM1250833MEG00748 | E100: Machine | F100: 1796 | G100: Replacement | I100: Submitted | J100: [ZNF0111AG-ME] Rotimatic Next (Black & Grey) | K100: 0 | L100: 1 | M100: Return with Refund/Replacement | N100: ZM1250833MEG00748 roti count: 1796 Press Pan stuck | O100: ZM1250833MEG00748 ROTI COUNT:: 1796 PRESS PAN STUCK
A101: 46227 | B101: Nobal Niraula | C101: 77396 | D101: ZM1260102CAG08289 | E101: Machine | F101: 123 | G101: Replacement | I101: Submitted | J101: [ZNF0111AW-CA] Rotimatic Next (Black & White) | K101: 37.127093 | L101: 1 | M101: Return with Refund/Replacement | N101: ZM1260102CAG08289 roti count: 123 Colour mismatch | O101: ZM1260102CAG08289 ROTI COUNT:: 123 COLOUR MISMATCH
A102: 46227 | B102: Umesh Nitnaware | C102: RSO07881 | D102: ZM1260104CAW09015 | E102: Machine | F102: 192 | G102: Replacement | I102: Submitted | J102: [ZNF0111AG-CA] Rotimatic Next (Black & Grey) | K102: 0 | L102: 1 | M102: Return with Refund/Replacement | N102: ZM1260104CAW09015 roti count: 192 Loosed VT | O102: ZM1260104CAW09015 ROTI COUNT:: 192 LOOSE VERTICAL TRAY
A103: 46227 | B103: Shivank Goel | C103: 67211 | D103: ZM1250521CAG00414 | E103: Machine | F103: 1012 | G103: Replacement | I103: Submitted | J103: [ZNF0111AG-CA] Rotimatic Next (Black & Grey) | K103: 0 | L103: 1 | M103: Return with Refund/Replacement | N103: ZM1250521CAG00414 roti count: 1012 Cracked Side Cover | O103: ZM1250521CAG00414 ROTI COUNT:: 1012 CRACKED SIDE COVER
A104: 46227 | B104: Nitin Waghmode | C104: 62918 | D104: ZM1250626CAW01186 | E104: Machine | F104: 1857 | G104: Replacement | I104: Submitted | J104: [Extend-Protection-Plan-299.00] Extend Protection Plan - US - 2 Years (299.00) | K104: 0 | L104: 1 | M104: Return with Refund/Replacement | N104: ZM1250626CAW01186 roti count: 1857 Knead Blade Stuck | O104: ZM1250626CAW01186 ROTI COUNT:: 1857 KNEADER BLADE STUCK
... A117: 46226 | B117: Hemanth Buchireddy | C117: 71911 | D117: ZM1251144CAG04582 | E117: Machine | F117: 1340 | G117: Replacement | I117: Submitted | J117: [ZNF0111AG-CA] Rotimatic Next (Black & Grey) | K117: 41.744488 | L117: 1 | M117: Return with Refund/Replacement | N117: ZM1251144CAG04582 roti count: 1340 Press Pan Stuck | O117: ZM1251144CAG04582 ROTI COUNT:: 1340 PRESS PAN STUCK
A118: 46226 | B118: RAHUL NAIK | C118: 65257 | D118: ZM1250727MEW00228 | E118: Machine | F118: 2081 | G118: Replacement | H118: RSO08972 | I118: Processing | J118: [ZNF0111AW-ME] Rotimatic Next (Black & White) | K118: 145.47691 | L118: 1 | M118: Return with Refund/Replacement | N118: ZM1250727MEW00228 roti count: 2081 Stirrer Not Rotating | O118: ZM1250727MEW00228 ROTI COUNT:: 2081 STIRRER NOT ROTATING
A119: 46226 | B119: Ahalya Aripaka | C119: 69163 | D119: ZM1250834CAG02363 | E119: Machine | F119: 301 | G119: Replacement | I119: Submitted | J119: [ZNF0111AG-CA] Rotimatic Next (Black & Grey) | K119: 0 | L119: 1 | M119: Return with Refund/Replacement | N119: ZM1250834CAG02363 roti count: 301 Top Casing Crack | O119: ZM1250834CAG02363 ROTI COUNT:: 301 TOP CASING CRACK
A120: 46226 | B120: Jagjeevan Gopireddy | C120: 79908 | D120: ZM1260417CAG10141 | E120: Machine | F120: 107 | G120: Replacement | I120: Submitted | J120: [ZNF0111AG-CA] Rotimatic Next (Black & Grey) | K120: 35.996784 | L120: 1 | M120: Return with Refund/Replacement | N120: ZM1260417CAG10141 roti count: 107 Not Powering On | O120: ZM1260417CAG10141 ROTI COUNT:: 107 NOT NOT POWERING ON
A121: 46226 | B121: Kanwarpal Singh | C121: 81397 | D121: ZM1250833MEG00776 | E121: Machine | F121: 676 | G121: Replacement | I121: Submitted | J121: [2YearRotimaticNextRotimaticCareWarranty] Rotimatic Next - Rotimatic Care Plus Warranty - 2 Years | K121: 0 | L121: 1 | M121: Return with Refund/Replacement | N121: ZM1250833MEG00776 roti count: 676 Press Pan Stuck | O121: ZM1250833MEG00776 ROTI COUNT:: 676 PRESS PAN STUCK
A122: 46226 | B122: Anamika Sharma | C122: 64016 | D122: ZM1250624CAG00714 | E122: Machine | F122: 35 | G122: Replacement | I122: Submitted | J122: [Extend-Protection-Plan-299.00] Extend Protection Plan - US - 2 Years (299.00) | K122: 0 | L122: 1 | M122: Return with Refund/Replacement | N122: ZM1250624CAG00714 roti count: 35 Not Powering On | O122: ZM1250624CAG00714 ROTI COUNT:: 35 NOT NOT POWERING ON
A123: 46226 | B123: Rajeev Agnihotri | C123: 79268 | D123: ZM1260102CAG08391 | E123: Machine | F123: 91 | G123: Replacement | I123: Submitted | J123: [ZNF0111AG-CA] Rotimatic Next (Black & Grey) | K123: 49.416819 | L123: 1 | M123: Return with Refund/Replacement | N123: ZM1260102CAG08391 roti count: 91 Cannot Transfer Doughball | O123: ZM1260102CAG08391 ROTI COUNT:: 91 CANNOT TRANSFER DOUGH BALL
A124: 46226 | B124: Anita Pathak | C124: 65407 | D124: ZM1250832CAW02053 | E124: Machine | F124: 226 | G124: Replacement | I124: Submitted | J124: [ZNF0111AW-CA] Rotimatic Next (Black & White) | K124: 0 | L124: 1 | M124: Return with Refund/Replacement | N124: ZM1250832CAW02053 roti count: 226 Transfer Arm Stuck | O124: ZM1250832CAW02053 ROTI COUNT:: 226 TRANSFER ARM STUCK
A125: 46226 | B125: Tushar Gupta | C125: 70461 | D125: ZM1251043CAG03713 | E125: Machine | F125: 733 | G125: Replacement | I125: Submitted | J125: [ZNF0111AG-CA] Rotimatic Next (Black & Grey) | K125: 44.749474 | L125: 1 | M125: Return with Refund/Replacement | N125: ZM1251043CAG03713 roti count: 733 Top Casing Crack | O125: ZM1251043CAG03713 ROTI COUNT:: 733 TOP CASING CRACK
A126: 46226 | B126: Jaswinder Kaur | C126: 73405 | D126: ZM1251147CAG05391 | E126: Machine | F126: 1817 | G126: Replacement | I126: Submitted | J126: [2YearRotimaticNextRotimaticCareWarranty] Rotimatic Next - Rotimatic Care Plus Warranty - 2 Years | K126: 0 | L126: 1 | M126: Return with Refund/Replacement | N126: ZM1251147CAG05391 roti count: 1817 Transfer Arm Stuck | O126: ZM1251147CAG05391 ROTI COUNT:: 1817 TRANSFER ARM STUCK
A127: 46226 | B127: satish bomble | C127: 76028 | D127: ZM1260206MEG02526 | E127: Machine | F127: 1735 | G127: Replacement | I127: Submitted | J127: [ZNF0111AG-ME] Rotimatic Next (Black & Grey) | K127: 82.076524 | L127: 1 | M127: Return with Refund/Replacement | N127: ZM1260206MEG02526 roti count: 1735 Transfer Arm Stuck | O127: ZM1260206MEG02526 ROTI COUNT:: 1735 TRANSFER ARM STUCK
A128: 46226 | B128: Saurabh Vilekar | C128: 77327 | D128: ZM1260208CAG09749 | E128: Machine | F128: 88 | G128: Replacement | I128: Submitted | J128: [3YearRotimaticNextRotimaticCareWarranty] Rotimatic Next - Rotimatic Care Plus Warranty - 3 Years | K128: 33.625385 | L128: 1 | M128: Return with Refund/Replacement | N128: ZM1260208CAG09749 roti count: 88 Not Powering On | O128: ZM1260208CAG09749 ROTI COUNT:: 88 NOT NOT POWERING ON
A129: 46226 | B129: Manju Dhankar | C129: RSO06363 | D129: ZM1251251CAG06919 | E129: Machine | F129: 291 | G129: Replacement | I129: Submitted | J129: [ZNF0111AG-CA] Rotimatic Next (Black & Grey) | K129: 0 | L129: 1 | M129: Return with Refund/Replacement | N129: ZM1251251CAG06919 roti count: 291 Slave communication Error | O129: ZM1251251CAG06919 ROTI COUNT:: 291 SLAVE COMMUNICATION ERROR
A130: 46226 | B130: Sinthia Mondal | C130: 72251 | D130: ZM1250938CAG03079 | E130: Machine | F130: 1514 | G130: Replacement | H130: RSO08971 | I130: Processing | J130: [ZNF0111AG-CA] Rotimatic Next (Black & Grey) | K130: 45.142679 | L130: 1 | M130: Return with Refund/Replacement | N130: ZM1250938CAG03079 roti count: 1514 Transfer Arm Stuck | O130: ZM1250938CAG03079 ROTI COUNT:: 1514 TRANSFER ARM STUCK
A131: 46226 | B131: Vinay Hosuru Siddappa | C131: 69244 | D131: ZM1250835CAG02650 | E131: Machine | F131: 1183 | G131: Replacement | I131: Submitted | J131: [3YearRotimaticNextRotimaticCareWarranty] Rotimatic Next - Rotimatic Care Plus Warranty - 3 Years | K131: 40.581641 | L131: 1 | M131: Return with Refund/Replacement | N131: ZM1250835CAG02650 roti count: 1183 Kneader Tray Stuck | O131: ZM1250835CAG02650 ROTI COUNT:: 1183 KNEADER TRAY STUCK
A132: 46226 | B132: Karan Arora | C132: 64920 | D132: ZM1250625CAG00973 | E132: Machine | F132: 11 | G132: Replacement | I132: Submitted | J132: [ZNF0111AG-CA] Rotimatic Next (Black & Grey) | K132: 0 | L132: 1 | M132: Return with Refund/Replacement | N132: ZM1250625CAG00973 roti count: 11 Not Poweering On | O132: ZM1250625CAG00973 ROTI COUNT:: 11 NOT POWEERING ON
A133: 46226 | B133: Riddhi Vasadia | C133: 68960 | D133: ZM1250938CAG03068 | E133: Machine | F133: 1095 | G133: Replacement | I133: Submitted | J133: [3YearRotimaticNextRotimaticCareWarranty] Rotimatic Next - Rotimatic Care Plus Warranty - 3 Years | K133: 141.08091 | L133: 1 | M133: Return with Refund/Replacement | N133: ZM1250938CAG03068 roti count: 1095 Kneader Tray Stuck | O133: ZM1250938CAG03068 ROTI COUNT:: 1095 KNEADER TRAY STUCK
A134: 46226 | B134: Rashmi Babtiwale | C134: 59127 | D134: ZM82408CAB19B | E134: Machine | F134: 2173 | G134: Replacement | I134: Submitted | J134: [ZMA0217] Roti Basket | K134: 35.028415 | L134: 1 | M134: Return with Refund/Replacement | N134: ZM82408CAB19B roti count: 2173 Stirrer is not rotating | O134: ZM82408CAB19B ROTI COUNT:: 2173 STIRRER NOT ROTATING
A135: 46226 | B135: Mohit Madken | C135: 69620 | D135: ZM1250940CAW03454 | E135: Machine | F135: 507 | G135: Replacement | I135: Submitted | J135: [ZNF0111AW-CA] Rotimatic Next (Black & White) | K135: 43.393373 | L135: 1 | M135: Return with Refund/Replacement | N135: ZM1250940CAW03454 roti count: 507 Cannot Connect to Wifi | O135: ZM1250940CAW03454 ROTI COUNT:: 507 CANNOT CONNECT TO WI-FI
A136: 46226 | B136: Yogesh Pandey | C136: 74166 | D136: ZM1260208CAG09612 | E136: Machine | F136: 507 | G136: Replacement | I136: Submitted | J136: [2YearRotimaticNextRotimaticCareWarranty] Rotimatic Next - Rotimatic Care Plus Warranty - 2 Years | K136: 181.93826 | L136: 1 | M136: Return with Refund/Replacement | N136: ZM1260208CAG09612 roti count: 507 Not Powering On | O136: ZM1260208CAG09612 ROTI COUNT:: 507 NOT NOT POWERING ON
A137: 46226 | B137: Siva Narendra Prasad Janumpally | C137: 74269 | D137: ZM1251249MEG02071 | E137: Machine | F137: 1158 | G137: Replacement | H137: RSO08963 | I137: Processing | J137: [ZNF0111AG-ME] Rotimatic Next (Black & Grey) | K137: 0 | L137: 1 | M137: Return with Refund/Replacement | N137: ZM1251249MEG02071 roti count: 1158 Dispensing Position Not Correct | O137: ZM1251249MEG02071 ROTI COUNT:: 1158 DISPENSING POSITION NOT CORRECT
A138: 46226 | B138: HARIKRUSHNA PATEL | C138: 75701 | D138: ZM1251251CAG07063 | E138: Machine | F138: 1023 | G138: Replacement | I138: Submitted | J138: [2YearRotimaticNextRotimaticCareWarranty] Rotimatic Next - Rotimatic Care Plus Warranty - 2 Years | K138: 138.10247 | L138: 1 | M138: Return with Refund/Replacement | N138: ZM1251251CAG07063 roti count: 1023 Press Pan Stuck | O138: ZM1251251CAG07063 ROTI COUNT:: 1023 PRESS PAN STUCK
A139: 46226 | B139: Veerabhadra Nemani | C139: 75926 | D139: ZM1260104CAW09026 | E139: Machine | F139: 132 | G139: Replacement | I139: Submitted | J139: [ZNF0111AW-CA] Rotimatic Next (Black & White) | K139: 37.271347 | L139: 1 | M139: Return with Refund/Replacement | N139: ZM1260104CAW09026 roti count: 132 Not Powering On | O139: ZM1260104CAW09026 ROTI COUNT:: 132 NOT NOT POWERING ON
A140: 46226 | B140: Sandip Tayade | C140: RSO06489 | D140: ZM1260206CAG09453 | E140: Machine | F140: 239 | G140: Replacement | I140: Submitted | J140: [ZNF0111AG-CA] Rotimatic Next (Black & Grey) | K140: 0 | L140: 1 | M140: Return with Refund/Replacement | N140: ZM1260206CAG09453 roti count: 239 Pans Not Heating | O140: ZM1260206CAG09453 ROTI COUNT:: 239 PANS NOT HEATING
A141: 46226 | B141: Gaurav Sutaria | C141: RSO07972 | D141: ZM1260104CAW08880 | E141: Machine | F141: 70 | G141: Replacement | I141: Submitted | J141: [ZNF0111AG-CA] Rotimatic Next (Black & Grey) | K141: 0 | L141: 1 | M141: Return with Refund/Replacement | N141: ZM1260104CAW08880 roti count: 70 Not Powering On | O141: ZM1260104CAW08880 ROTI COUNT:: 70 NOT NOT POWERING ON
A142: 46226 | B142: Sadique Rahman | C142: 74433 | D142: ZM1251251CAG07432 | E142: Machine | F142: 1098 | G142: Replacement | I142: Submitted | J142: [ZNF0111AG-CA] Rotimatic Next (Black & Grey) | K142: 0 | L142: 1 | M142: Return with Refund/Replacement | N142: ZM1251251CAG07432 roti count: 1098 Stuck on Checking Screen | O142: ZM1251251CAG07432 ROTI COUNT:: 1098 STUCK ON CHECKING SCREEN
A143: 46226 | B143: Abha Bukharia | C143: 76222 | D143: ZM1260104CAW08797 | E143: Machine | F143: 302 | G143: Replacement | I143: Submitted | J143: [ZNF0111AW-CA] Rotimatic Next (Black & White) | K143: 36.988144 | L143: 1 | M143: Return with Refund/Replacement | N143: ZM1260104CAW08797 roti count: 302 Not Powering On | O143: ZM1260104CAW08797 ROTI COUNT:: 302 NOT NOT POWERING ON
A144: 46225 | B144: Robin Chandil | C144: 78583 | D144: ZM1260417CAW10378 | E144: Machine | F144: 352 | G144: Replacement | I144: Submitted | J144: [2YearRotimaticNextRotimaticCareWarranty] Rotimatic Next - Rotimatic Care Plus Warranty - 2 Years | K144: 165.03112 | L144: 1 | M144: Return with Refund/Replacement | N144: ZM1260417CAW10378 roti count: 352 VT Stuck | O144: ZM1260417CAW10378 ROTI COUNT:: 352 VERTICAL TRAY STUCK
A145: 46225 | B145: Achal Dave | C145: 79532 | D145: ZM1260209MEG02947 | E145: Machine | F145: 163 | G145: Replacement | H145: RSO08962 | I145: Processing | J145: [3YearRotimaticNextRotimaticCareWarranty] Rotimatic Next - Rotimatic Care Plus Warranty - 3 Years | K145: 119.27744 | L145: 1 | M145: Return with Refund/Replacement | N145: ZM1260209MEG02947 roti count: 163 Kneading tray is stuck | O145: ZM1260209MEG02947 ROTI COUNT:: 163 KNEADING TRAY IS STUCK
A146: 46225 | B146: Akhil Reddy Sabhapathi | C146: 65327 | D146: ZM1250729CAG01659 | E146: Machine | F146: 13 | G146: Replacement | I146: Submitted | J146: [ZNF0111AG-CA] Rotimatic Next (Black & Grey) | K146: 0 | L146: 1 | M146: Return with Refund/Replacement | N146: ZM1250729CAG01659 roti count: 13 Rattling Noise | O146: ZM1250729CAG01659 ROTI COUNT:: 13 RATTLING NOISE
A147: 46225 | B147: Sarthak Arora | C147: 73058 | D147: ZM1251147CAG05568 | E147: Machine | F147: 29 | G147: Replacement | I147: Submitted | J147: [ZNF0111AG-CA] Rotimatic Next (Black & Grey) | K147: 198.24938 | L147: 1 | M147: Return with Refund/Replacement | N147: ZM1251147CAG05568 roti count: 29 Flour Spillage | O147: ZM1251147CAG05568 ROTI COUNT:: 29 FLOUR SPILLAGE
...
